Workbook

Sheet Item
A1: ##var | B1: Id | C1: Name | D1: Alias | E1: ItemType | F1: BuildChannelMask | G1: HiddenRegionFlag | H1: SafeResourceId | I1: ItemRarity | J1: SortOrder | K1: IsHiddenInBag | L1: AcquisitionType | M1: VisualZOffset | O1: *AssetPathList | P1: IconPath | Q1: SkinId | S1: SteamItemDefId | T1: SteamItemDefType | U1: SteamDescription | V1: SteamGameOnly | W1: SteamTradable | X1: SteamMarketable | Y1: SteamAutoStack | Z1: SteamHidden | AA1: SteamDisplayType | AB1: SteamTags | AC1: SteamIconUrl | AD1: SteamIconUrlLarge
A2: ##type | B2: int | C2: string | D2: string | E2: EItemType | F2: EBuildChannelMask | G2: EHiddenRegionFlag | H2: int | I2: ERarity | J2: int | K2: bool | L2: EAcquisitionType | M2: int | O2: list,string | P2: string | Q2: int | S2: int | T2: ESteamItemDefType | U2: string | V2: bool | W2: bool | X2: bool | Y2: bool | Z2: bool | AA2: string | AB2: string | AC2: string | AD2: string
A3: ## | D3: 内部名称方便记忆 | G3: 在哪些国家无法抽到 | H3: 直播安全模式开启状态下，需要替换成和谐资源，该替换规则高于地区规则 | J3: 排序权重，数字越小约靠前 | M3: 调整物品相对于所属装备位默认层级的本地 Z 值。0 保持默认层级，正数向前，负数向后。仅对已接入该字段的装扮类型生效。帽子填写 0 时挡住眼镜，填写 -1 时被眼镜挡住。 | O3: 由于部件拆的比较碎，因此需要文件夹路径如 `Assets\Eyewear\EyePatch.png` 拿到字符串后需要自行转义 该字段为列表，可以跨行填写多个 要注意，也可以是tres文件 由于小狗皮肤由多个文件组成，因此直接填写文件夹目录，卡面也是填文件夹 | P3: 在背包内显示的图标 | S3: Steam itemdef ID。现阶段可填 0 | T3: Steam 类型。现阶段普通物品可先填 Item 或空 | U3: Steam 后台英文说明；game_only 回执不向玩家展示 | V3: 在Steam页面背包中隐藏 默认 true | W3: 默认 false | X3: 默认 false | Y3: Refreshment 可 true，装扮 false | Z3: 正式物品默认 false | AA3: 可空 | AB3: 稀有度标签由转换器填写； 自定义标签填写英文小写字母例如color:red; | AC3: 可空 | AD3: 可空
A4: ## | B4: id | C4: 显示名称 | D4: 策划名称 | E4: 物品类型 | F4: 适用构建渠道 | G4: 在哪些国家无法抽到 | H4: 安全替换资源id | I4: 品质 | J4: 排序权重 | K4: 在背包中隐藏 | L4: 投放类型 | M4: 视觉层级偏移 | O4: 对应素材图片路径材列表 | P4: 图标路径 | Q4: 皮肤id | S4: Steam定义物品ID | T4: 定义类型 | U4: 英文说明 | V4: 为游戏内专用 | W4: 可交易 | X4: 可在市场出售 | Y4: 自动堆叠 | Z4: Steam隐藏 | AA4: 显示类型 | AB4: 自定义标签 | AC4: 小图标 | AD4: 大图标
B5: 1001 | C5: Red Shiba Inu | D5: 原色赤柴 | E5: Dog | F5: Playtest|Release|Demo | I5: 普通 | J5: 200 | K5: FALSE | L5: 初始拥有 | M5: 0 | O5: v3\Shiba\Red\ | P5: v3\ItemIcon\Dog_1001.png | Q5: 1001 | T5: Item | V5: TRUE | W5: FALSE | X5: FALSE | Y5: FALSE | Z5: FALSE
B6: 1002 | C6: Chubby Black Shiba | D6: 胖黑柴 | E6: Dog | F6: Playtest|Release | I6: 稀有 | J6: 200 | K6: FALSE | L6: 装扮盲盒产出 | M6: 0 | O6: v3\Shiba\Black\ | P6: v3\ItemIcon\Dog_1002.png | Q6: 1002 | S6: 101002 | T6: Item | V6: TRUE | W6: FALSE | X6: FALSE | Y6: FALSE | Z6: FALSE
B7: 1003 | C7: Chubby Cream Shiba | D7: 胖白柴 | E7: Dog | F7: Playtest|Release | I7: 优秀 | J7: 200 | K7: FALSE | L7: 装扮盲盒产出 | M7: 0 | O7: v3\Shiba\Cream\ | P7: v3\ItemIcon\Dog_1003.png | Q7: 1003 | S7: 101003 | T7: Item | V7: TRUE | W7: FALSE | X7: FALSE | Y7: FALSE | Z7: FALSE
B8: 1004 | C8: Chubby Sesame Shiba | D8: 胖胡麻柴 | E8: Dog | F8: Playtest|Release | I8: 优秀 | J8: 200 | K8: FALSE | L8: 装扮盲盒产出 | M8: 0 | O8: v3\Shiba\Sesame\ | P8: v3\ItemIcon\Dog_1004.png | Q8: 1004 | S8: 101004 | T8: Item | V8: TRUE | W8: FALSE | X8: FALSE | Y8: FALSE | Z8: FALSE
B9: 1005 | C9: Chubby Red Shiba | D9: 胖赤柴 | E9: Dog | F9: Playtest|Release | I9: 史诗 | J9: 100 | K9: FALSE | L9: 装扮盲盒产出 | M9: 0 | O9: v3\Shiba\Red\ | P9: v3\ItemIcon\Dog_1005.png | Q9: 1005 | S9: 101005 | T9: Item | V9: TRUE | W9: FALSE | X9: FALSE | Y9: FALSE | Z9: FALSE
B10: 1006 | C10: Arcade Gamer Red Shiba | D10: 电玩赤柴 | E10: Dog | F10: Playtest|Release | I10: 传说 | J10: 100 | K10: FALSE | L10: 装扮盲盒产出 | M10: 0 | O10: v3\Shiba\Red\ | P10: v3\ItemIcon\Dog_1006.png | Q10: 1006 | S10: 101006 | T10: Item | V10: TRUE | W10: FALSE | X10: FALSE | Y10: FALSE | Z10: FALSE
B11: 1007 | C11: Esports Pro Black Shiba | D11: 电竞黑柴 | E11: Dog | F11: Playtest|Release | I11: 史诗 | J11: 100 | K11: FALSE | L11: 装扮盲盒产出 | M11: 0 | O11: v3\Shiba\Black\ | P11: v3\ItemIcon\Dog_1007.png | Q11: 1007 | S11: 101007 | T11: Item | V11: TRUE | W11: FALSE | X11: FALSE | Y11: FALSE | Z11: FALSE
B12: 1008 | C12: Gamer Girl Cream Shiba | D12: 电玩妹白柴 | E12: Dog | F12: Playtest|Release|Demo | I12: 传说 | J12: 100 | K12: FALSE | L12: 装扮盲盒产出 | M12: 0 | O12: v3\Shiba\Cream\ | P12: v3\ItemIcon\Dog_1008.png | Q12: 1008 | S12: 101008 | T12: Item | V12: TRUE | W12: FALSE | X12: FALSE | Y12: FALSE | Z12: FALSE
B13: 1009 | C13: Scholar Black Shiba | D13: 学者黑柴 | E13: Dog | F13: Playtest|Release | I13: 传说 | J13: 100 | K13: FALSE | L13: 装扮盲盒产出 | M13: 0 | O13: v3\Shiba\Black\ | P13: v3\ItemIcon\Dog_1009.png | Q13: 1009 | S13: 101009 | T13: Item | V13: TRUE | W13: FALSE | X13: FALSE | Y13: FALSE | Z13: FALSE
B14: 1010 | C14: Aristocrat Cream Shiba | D14: 贵族白柴 | E14: Dog | F14: Playtest|Release | I14: 传说 | J14: 100 | K14: FALSE | L14: 装扮盲盒产出 | M14: 0 | O14: v3\Shiba\Cream\ | P14: v3\ItemIcon\Dog_1010.png | Q14: 1010 | S14: 101010 | T14: Item | V14: TRUE | W14: FALSE | X14: FALSE | Y14: FALSE | Z14: FALSE
B15: 1011 | C15: Top Student Sesame Shiba | D15: 学霸胡麻柴 | E15: Dog | F15: Playtest|Release|Demo | I15: 神话 | J15: 100 | K15: FALSE | L15: 装扮盲盒产出 | M15: 0 | O15: v3\Shiba\Sesame\ | P15: v3\ItemIcon\Dog_1011.png | Q15: 1011 | S15: 101011 | T15: Item | V15: TRUE | W15: FALSE | X15: FALSE | Y15: FALSE | Z15: FALSE
B16: 1012 | C16: Gentleman Red Shiba | D16: 绅士赤柴 | E16: Dog | F16: Playtest|Release | I16: 史诗 | J16: 100 | K16: FALSE | L16: 装扮盲盒产出 | M16: 0 | O16: v3\Shiba\Red\ | P16: v3\ItemIcon\Dog_1012.png | Q16: 1012 | S16: 101012 | T16: Item | V16: TRUE | W16: FALSE | X16: FALSE | Y16: FALSE | Z16: FALSE
B17: 1013 | C17: Upperclassman Red Shiba | D17: 学长赤柴 | E17: Dog | F17: Playtest|Release|Demo | I17: 史诗 | J17: 100 | K17: FALSE | L17: 装扮盲盒产出 | M17: 0 | O17: v3\Shiba\Red\ | P17: v3\ItemIcon\Dog_1013.png | Q17: 1013 | S17: 101013 | T17: Item | V17: TRUE | W17: FALSE | X17: FALSE | Y17: FALSE | Z17: FALSE
... B41: 1037 | C41: Night Owl Sesame Shiba | D41: 夜客胡麻柴 | E41: Dog | F41: Playtest|Release | I41: 传说 | J41: 100 | K41: FALSE | L41: 装扮盲盒产出 | M41: 0 | O41: v3\Shiba\Sesame\ | P41: v3\ItemIcon\Dog_1037.png | Q41: 1037 | S41: 101037 | T41: Item | V41: TRUE | W41: FALSE | X41: FALSE | Y41: FALSE | Z41: FALSE
A42: ##
B43: 2001 | C43: Green Beret | D43: 绿色贝雷帽 | E43: Headwear | F43: Playtest|Release | I43: 优秀 | J43: 300 | K43: FALSE | L43: 装扮盲盒产出 | M43: 0 | O43: v2\Headwear\Beret_Green.png | P43: v2\ItemIcon\Headwear_Beret_Green.png | S43: 102001 | T43: Item | V43: TRUE | W43: FALSE | X43: FALSE | Y43: FALSE | Z43: FALSE
B44: 2002 | C44: Red Beret | D44: 红色贝雷帽 | E44: Headwear | F44: Playtest|Release | I44: 稀有 | J44: 300 | K44: FALSE | L44: 装扮盲盒产出 | M44: 0 | O44: v2\Headwear\Beret_Red.png | P44: v2\ItemIcon\Headwear_Beret_Red.png | S44: 102002 | T44: Item | V44: TRUE | W44: FALSE | X44: FALSE | Y44: FALSE | Z44: FALSE
B45: 2003 | C45: Gray Fedora Hat | D45: 灰色软呢帽 | E45: Headwear | F45: Playtest|Release|Demo | I45: 优秀 | J45: 300 | K45: FALSE | L45: 装扮盲盒产出 | M45: 0 | O45: v2\Headwear\FedoraHat_Gray.png | P45: v2\ItemIcon\Headwear_FedoraHat_Gray.png | S45: 102003 | T45: Item | V45: TRUE | W45: FALSE | X45: FALSE | Y45: FALSE | Z45: FALSE
B46: 2004 | C46: Maroon Fedora Hat | D46: 栗色软呢帽 | E46: Headwear | F46: Playtest|Release | I46: 稀有 | J46: 300 | K46: FALSE | L46: 装扮盲盒产出 | M46: 0 | O46: v2\Headwear\FedoraHat_Maroon.png | P46: v2\ItemIcon\Headwear_FedoraHat_Maroon.png | S46: 102004 | T46: Item | V46: TRUE | W46: FALSE | X46: FALSE | Y46: FALSE | Z46: FALSE
B47: 2005 | C47: Halo | D47: 光环 | E47: Headwear | F47: Playtest|Release | I47: 传说 | J47: 300 | K47: FALSE | L47: 装扮盲盒产出 | M47: 0 | O47: v2\Headwear\Hole.png | P47: v2\ItemIcon\Headwear_Hole.png | S47: 102005 | T47: Item | V47: TRUE | W47: FALSE | X47: FALSE | Y47: FALSE | Z47: FALSE
B48: 2006 | C48: Lucky Hat | D48: 幸运帽 | E48: Headwear | F48: Playtest|Release | I48: 稀有 | J48: 300 | K48: FALSE | L48: 装扮盲盒产出 | M48: 0 | O48: v2\Headwear\LuckyHat.png | P48: v2\ItemIcon\Headwear_LuckyHat.png | S48: 102006 | T48: Item | V48: TRUE | W48: FALSE | X48: FALSE | Y48: FALSE | Z48: FALSE
B49: 2007 | C49: Black Magic Hat | D49: 黑色魔术帽 | E49: Headwear | F49: Playtest|Release | I49: 优秀 | J49: 300 | K49: FALSE | L49: 装扮盲盒产出 | M49: 0 | O49: v2\Headwear\MagicHat_Black.png | P49: v2\ItemIcon\Headwear_MagicHat_Black.png | S49: 102007 | T49: Item | V49: TRUE | W49: FALSE | X49: FALSE | Y49: FALSE | Z49: FALSE
B50: 2008 | C50: White Magic Hat | D50: 白色魔术帽 | E50: Headwear | F50: Playtest|Release | I50: 史诗 | J50: 300 | K50: FALSE | L50: 装扮盲盒产出 | M50: 0 | O50: v2\Headwear\MagicHat_White.png | P50: v2\ItemIcon\Headwear_MagicHat_White.png | S50: 102008 | T50: Item | V50: TRUE | W50: FALSE | X50: FALSE | Y50: FALSE | Z50: FALSE
B51: 2009 | C51: Beige Sun Hat | D51: 米色太阳帽 | E51: Headwear | F51: Playtest|Release|Demo | I51: 优秀 | J51: 300 | K51: FALSE | L51: 装扮盲盒产出 | M51: 0 | O51: v2\Headwear\SunHat_Beige.png | P51: v2\ItemIcon\Headwear_SunHat_Beige.png | S51: 102009 | T51: Item | V51: TRUE | W51: FALSE | X51: FALSE | Y51: FALSE | Z51: FALSE
B52: 2010 | C52: Blue Sun Hat | D52: 蓝色太阳帽 | E52: Headwear | F52: Playtest|Release | I52: 史诗 | J52: 300 | K52: FALSE | L52: 装扮盲盒产出 | M52: 0 | O52: v2\Headwear\SunHat_Blue.png | P52: v2\ItemIcon\Headwear_SunHat_Blue.png | S52: 102010 | T52: Item | V52: TRUE | W52: FALSE | X52: FALSE | Y52: FALSE | Z52: FALSE
B53: 2011 | C53: Red Tyrolean Hat | D53: 红色蒂罗尔帽 | E53: Headwear | F53: Playtest|Release | I53: 稀有 | J53: 300 | K53: FALSE | L53: 装扮盲盒产出 | M53: 0 | O53: v2\Headwear\TyroleanHat_Red.png | P53: v2\ItemIcon\Headwear_TyroleanHat_Red.png | S53: 102011 | T53: Item | V53: TRUE | W53: FALSE | X53: FALSE | Y53: FALSE | Z53: FALSE
B54: 2012 | C54: Green Tyrolean Hat | D54: 绿色蒂罗尔帽 | E54: Headwear | F54: Playtest|Release | I54: 优秀 | J54: 300 | K54: FALSE | L54: 装扮盲盒产出 | M54: 0 | O54: v2\Headwear\TyroleanHat_Green.png | P54: v2\ItemIcon\Headwear_TyroleanHat_Green.png | S54: 102012 | T54: Item | V54: TRUE | W54: FALSE | X54: FALSE | Y54: FALSE | Z54: FALSE
... B76: 2034 | C76: Autumn 2026 Graduation Cap | D76: 2026秋季 学士帽 | E76: Headwear | F76: Playtest|Release|Demo | I76: 特殊1 | J76: 100 | K76: FALSE | L76: 活动产出 | M76: 0 | O76: v2\Headwear\GraduationCap_Autumn2026.png | P76: v2\ItemIcon\Headwear_GraduationCap_Autumn2026.png | S76: 102034 | T76: Item | V76: TRUE | W76: FALSE | X76: FALSE | Y76: FALSE | Z76: FALSE
A77: ## | B77: 3001-3005墓碑 | C77: 3D Glasses | D77: 3D眼镜 | E77: Eyewear | F77: Playtest|Release | I77: 优秀 | J77: 0 | K77: TRUE | L77: 已下架 | O77: v1\Eyewear\3DGlasses.png | P77: v1\ItemIcon\Eyewear_3DGlasses.png | S77: 103001 | T77: Item | V77: TRUE | W77: FALSE | X77: FALSE | Y77: FALSE | Z77: TRUE
B78: 4001 | C78: Type 1 | D78: 手臂颜色类型1 | E78: Arm | F78: Playtest|Release|Demo | G78: 全球 | I78: 普通 | J78: 0 | K78: TRUE | L78: 初始拥有 | M78: 0 | O78: v1\Player\Arm\Type1.png | P78: v1\ItemIcon\Arm_Type1.png | S78: 104001 | T78: Item | V78: TRUE | W78: FALSE | X78: FALSE | Y78: FALSE | Z78: FALSE
B79: 4002 | C79: Type 2 | D79: 手臂颜色类型2 | E79: Arm | F79: Playtest|Release|Demo | G79: 全球 | I79: 普通 | J79: 0 | K79: TRUE | L79: 初始拥有 | M79: 0 | O79: v1\Player\Arm\Type2.png | P79: v1\ItemIcon\Arm_Type2.png | S79: 104002 | T79: Item | V79: TRUE | W79: FALSE | X79: FALSE | Y79: FALSE | Z79: FALSE
B80: 4003 | C80: Type 3 | D80: 手臂颜色类型3 | E80: Arm | F80: Playtest|Release|Demo | G80: 全球 | I80: 普通 | J80: 0 | K80: TRUE | L80: 初始拥有 | M80: 0 | O80: v1\Player\Arm\Type3.png | P80: v1\ItemIcon\Arm_Type3.png | S80: 104003 | T80: Item | V80: TRUE | W80: FALSE | X80: FALSE | Y80: FALSE | Z80: FALSE
B81: 4004 | C81: Type 4 | D81: 手臂颜色类型4 | E81: Arm | F81: Playtest|Release|Demo | G81: 全球 | I81: 普通 | J81: 0 | K81: TRUE | L81: 初始拥有 | M81: 0 | O81: v1\Player\Arm\Type4.png | P81: v1\ItemIcon\Arm_Type4.png | S81: 104004 | T81: Item | V81: TRUE | W81: FALSE | X81: FALSE | Y81: FALSE | Z81: FALSE
B82: 4005 | C82: Type 5 | D82: 手臂颜色类型5 | E82: Arm | F82: Playtest|Release|Demo | G82: 全球 | I82: 普通 | J82: 0 | K82: TRUE | L82: 初始拥有 | M82: 0 | O82: v1\Player\Arm\Type5.png | P82: v1\ItemIcon\Arm_Type5.png | S82: 104005 | T82: Item | V82: TRUE | W82: FALSE | X82: FALSE | Y82: FALSE | Z82: FALSE
B83: 4006 | C83: Type 6 | D83: 手臂颜色类型6 | E83: Arm | F83: Playtest|Release|Demo | G83: 全球 | I83: 普通 | J83: 0 | K83: TRUE | L83: 初始拥有 | M83: 0 | O83: v1\Player\Arm\Type6.png | P83: v1\ItemIcon\Arm_Type6.png | S83: 104006 | T83: Item | V83: TRUE | W83: FALSE | X83: FALSE | Y83: FALSE | Z83: FALSE
B84: 5001 | C84: Baseball Jacket Black | D84: 黑色棒球夹克 | E84: Clothes | F84: Playtest|Release | I84: 优秀 | J84: 300 | K84: FALSE | L84: 装扮盲盒产出 | M84: 0 | O84: v1\Player\Clothes\BaseballJacket_Black.png | P84: v1\ItemIcon\Clothes_BaseballJacket_Black.png | S84: 105001 | T84: Item | V84: TRUE | W84: FALSE | X84: FALSE | Y84: FALSE | Z84: FALSE
B85: 5002 | C85: Baseball Jacket Purple | D85: 紫色棒球夹克 | E85: Clothes | F85: Playtest|Release | I85: 史诗 | J85: 300 | K85: FALSE | L85: 装扮盲盒产出 | M85: 0 | O85: v1\Player\Clothes\BaseballJacket_Purple.png | P85: v1\ItemIcon\Clothes_BaseballJacket_Purple.png | S85: 105002 | T85: Item | V85: TRUE | W85: FALSE | X85: FALSE | Y85: FALSE | Z85: FALSE
B86: 5003 | C86: Black Business Suit | D86: 黑色西装 | E86: Clothes | F86: Playtest|Release | I86: 稀有 | J86: 300 | K86: FALSE | L86: 装扮盲盒产出 | M86: 0 | O86: v1\Player\Clothes\BlackBusinessSuit_Black.png | P86: v1\ItemIcon\Clothes_BlackBusinessSuit_Black.png | S86: 105003 | T86: Item | V86: TRUE | W86: FALSE | X86: FALSE | Y86: FALSE | Z86: FALSE
B87: 5004 | C87: Blue Shirt | D87: 蓝色衬衫 | E87: Clothes | F87: Playtest|Release|Demo | I87: 史诗 | J87: 300 | K87: FALSE | L87: 装扮盲盒产出 | M87: 0 | O87: v1\Player\Clothes\BlueShirt_Cyan.png | P87: v1\ItemIcon\Clothes_BlueShirt_Cyan.png | S87: 105004 | T87: Item | V87: TRUE | W87: FALSE | X87: FALSE | Y87: FALSE | Z87: FALSE
B88: 5005 | C88: Blue Striped Shirt | D88: 蓝色条纹衬衫 | E88: Clothes | F88: Playtest|Release | I88: 史诗 | J88: 300 | K88: FALSE | L88: 装扮盲盒产出 | M88: 0 | O88: v1\Player\Clothes\BlueStripedShirt_RegattaStripe.png | P88: v1\ItemIcon\Clothes_BlueStripedShirt_RegattaStripe.png | S88: 105005 | T88: Item | V88: TRUE | W88: FALSE | X88: FALSE | Y88: FALSE | Z88: FALSE
B89: 5006 | C89: Cream Shirt | D89: 米色衬衫 | E89: Clothes | F89: Playtest|Release | I89: 优秀 | J89: 300 | K89: FALSE | L89: 装扮盲盒产出 | M89: 0 | O89: v1\Player\Clothes\CreamShirt_Beige.png | P89: v1\ItemIcon\Clothes_CreamShirt_Beige.png | S89: 105006 | T89: Item | V89: TRUE | W89: FALSE | X89: FALSE | Y89: FALSE | Z89: FALSE
B90: 5007 | C90: White Business Suit | D90: 白色西装 | E90: Clothes | F90: Playtest|Release | I90: 稀有 | J90: 300 | K90: FALSE | L90: 装扮盲盒产出 | M90: 0 | O90: v1\Player\Clothes\WhiteBusinessSuit_LightGray.png | P90: v1\ItemIcon\Clothes_WhiteBusinessSuit_LightGray.png | S90: 105007 | T90: Item | V90: TRUE | W90: FALSE | X90: FALSE | Y90: FALSE | Z90: FALSE
B91: 5008 | C91: White Shirt | D91: 白色衬衫 | E91: Clothes | F91: Playtest|Release|Demo | I91: 优秀 | J91: 300 | K91: FALSE | L91: 装扮盲盒产出 | M91: 0 | O91: v1\Player\Clothes\WhiteShirt_White.png | P91: v1\ItemIcon\Clothes_WhiteShirt_White.png | S91: 105008 | T91: Item | V91: TRUE | W91: FALSE | X91: FALSE | Y91: FALSE | Z91: FALSE
B92: 6001 | C92: Felt Emerald | D92: 翡翠绿桌布 | E92: Table | F92: Playtest|Release|Demo | I92: 普通 | J92: 300 | K92: FALSE | L92: 初始拥有 | M92: 0 | O92: v1\Table\Felt_Emerald.png | P92: v1\ItemIcon\Table_Felt_Emerald.png | S92: 106001 | T92: Item | V92: TRUE | W92: FALSE | X92: FALSE | Y92: FALSE | Z92: FALSE
B93: 6002 | C93: Red Bone | D93: 红骨桌布 | E93: Table | F93: Playtest|Release | I93: 史诗 | J93: 300 | K93: FALSE | L93: 装扮盲盒产出 | M93: 0 | O93: v1\Table\RedBone.png | P93: v1\ItemIcon\Table_RedBone.png | S93: 106002 | T93: Item | V93: TRUE | W93: FALSE | X93: FALSE | Y93: FALSE | Z93: FALSE
B94: 6003 | C94: Howl Club | D94: Howl Club桌布 | E94: Table | F94: Playtest|Release | I94: 史诗 | J94: 300 | K94: FALSE | L94: 装扮盲盒产出 | M94: 0 | O94: v1\Table\HowlClub.png | P94: v1\ItemIcon\Table_HowlClub.png | S94: 106003 | T94: Item | V94: TRUE | W94: FALSE | X94: FALSE | Y94: FALSE | Z94: FALSE
B95: 6004 | C95: Le Cercle Des Pattes | D95: Le Cercle Des Pattes桌布 | E95: Table | F95: Playtest|Release | I95: 稀有 | J95: 300 | K95: FALSE | L95: 装扮盲盒产出 | M95: 0 | O95: v1\Table\LeCercleDesPattes.png | P95: v1\ItemIcon\Table_LeCercleDesPattes.png | S95: 106004 | T95: Item | V95: TRUE | W95: FALSE | X95: FALSE | Y95: FALSE | Z95: FALSE
... B133: 9001 | C133: Black Tea | D133: 红茶 | E133: Refreshment | F133: Playtest|Release|Demo | I133: 史诗 | J133: 200 | K133: FALSE | L133: 消耗品盲盒产出 | M133: 0 | O133: v1\Treat\BlackTea.png | P133: v1\ItemIcon\Treat_BlackTea.png | S133: 109001 | T133: Item | V133: TRUE | W133: FALSE | X133: FALSE | Y133: TRUE | Z133: FALSE
B134: 9002 | C134: Bordeaux | D134: 波尔多 | E134: Refreshment | F134: Playtest|Release | G134: 沙特阿拉伯|阿联酋|马来西亚|印尼 | H134: 9009 | I134: 稀有 | J134: 200 | K134: FALSE | L134: 消耗品盲盒产出 | M134: 0 | O134: v1\Treat\Bordeaux.png | P134: v1\ItemIcon\Treat_Bordeaux.png | R134: 一些国家不允许饮酒，替换成水 | S134: 109002 | T134: Item | V134: TRUE | W134: FALSE | X134: FALSE | Y134: TRUE | Z134: FALSE
B135: 9003 | C135: Burgundy | D135: 勃艮第 | E135: Refreshment | F135: Playtest|Release | G135: 沙特阿拉伯|阿联酋|马来西亚|印尼 | H135: 9009 | I135: 稀有 | J135: 200 | K135: FALSE | L135: 消耗品盲盒产出 | M135: 0 | O135: v1\Treat\Burgundy.png | P135: v1\ItemIcon\Treat_Burgundy.png | R135: 一些国家不允许饮酒，替换成水 | S135: 109003 | T135: Item | V135: TRUE | W135: FALSE | X135: FALSE | Y135: TRUE | Z135: FALSE
B136: 9004 | C136: Champagne | D136: 香槟 | E136: Refreshment | F136: Playtest|Release|Demo | G136: 沙特阿拉伯|阿联酋|马来西亚|印尼 | H136: 9009 | I136: 史诗 | J136: 200 | K136: FALSE | L136: 消耗品盲盒产出 | M136: 0 | O136: v1\Treat\Chardonnay.png | P136: v1\ItemIcon\Treat_Chardonnay.png | R136: 一些国家不允许饮酒，替换成水 | S136: 109004 | T136: Item | V136: TRUE | W136: FALSE | X136: FALSE | Y136: TRUE | Z136: FALSE
B137: 9005 | C137: Shot Glass | D137: 子弹杯 | E137: Refreshment | F137: Playtest|Release | G137: 沙特阿拉伯|阿联酋|马来西亚|印尼 | H137: 9009 | I137: 稀有 | J137: 200 | K137: FALSE | L137: 消耗品盲盒产出 | M137: 0 | O137: v1\Treat\ShotGlass.png | P137: v1\ItemIcon\Treat_ShotGlass.png | R137: 一些国家不允许饮酒，替换成水 | S137: 109005 | T137: Item | V137: TRUE | W137: FALSE | X137: FALSE | Y137: TRUE | Z137: FALSE
B138: 9006 | C138: Tulip | D138: 郁金香杯 | E138: Refreshment | F138: Playtest|Release | G138: 沙特阿拉伯|阿联酋|马来西亚|印尼 | H138: 9009 | I138: 稀有 | J138: 200 | K138: FALSE | L138: 消耗品盲盒产出 | M138: 0 | O138: v1\Treat\Tulip.png | P138: v1\ItemIcon\Treat_Tulip.png | R138: 一些国家不允许饮酒，替换成水 | S138: 109006 | T138: Item | V138: TRUE | W138: FALSE | X138: FALSE | Y138: TRUE | Z138: FALSE
B139: 9007 | C139: Tumbler | D139: 平底杯 | E139: Refreshment | F139: Playtest|Release | G139: 沙特阿拉伯|阿联酋|马来西亚|印尼 | H139: 9009 | I139: 稀有 | J139: 200 | K139: FALSE | L139: 消耗品盲盒产出 | M139: 0 | O139: v1\Treat\Tumbler.png | P139: v1\ItemIcon\Treat_Tumbler.png | R139: 一些国家不允许饮酒，替换成水 | S139: 109007 | T139: Item | V139: TRUE | W139: FALSE | X139: FALSE | Y139: TRUE | Z139: FALSE
B140: 9008 | C140: Vintage | D140: 年份酒 | E140: Refreshment | F140: Playtest|Release | G140: 沙特阿拉伯|阿联酋|马来西亚|印尼 | H140: 9009 | I140: 史诗 | J140: 200 | K140: FALSE | L140: 消耗品盲盒产出 | M140: 0 | O140: v1\Treat\Vintage.png | P140: v1\ItemIcon\Treat_Vintage.png | R140: 一些国家不允许饮酒，替换成水 | S140: 109008 | T140: Item | V140: TRUE | W140: FALSE | X140: FALSE | Y140: TRUE | Z140: FALSE
B141: 9009 | C141: Water | D141: 凉白开 | E141: Refreshment | F141: Playtest|Release|Demo | I141: 优秀 | J141: 200 | K141: FALSE | L141: 消耗品盲盒产出 | M141: 0 | O141: v1\Treat\Water.png | P141: v1\ItemIcon\Treat_Water.png | R141: 一些国家不允许饮酒，替换成水 | S141: 109009 | T141: Item | V141: TRUE | W141: FALSE | X141: FALSE | Y141: TRUE | Z141: FALSE
B142: 9010 | C142: Whisky | D142: 威士忌 | E142: Refreshment | F142: Playtest|Release | G142: 沙特阿拉伯|阿联酋|马来西亚|印尼 | H142: 9009 | I142: 传说 | J142: 200 | K142: FALSE | L142: 消耗品盲盒产出 | M142: 0 | O142: v1\Treat\Whisky.png | P142: v1\ItemIcon\Treat_Whisky.png | S142: 109010 | T142: Item | V142: TRUE | W142: FALSE | X142: FALSE | Y142: TRUE | Z142: FALSE
B143: 9011 | C143: Whisky Cigar | D143: 威士忌雪茄 | E143: Refreshment | F143: Playtest|Release | G143: 沙特阿拉伯|阿联酋|马来西亚|印尼 | H143: 9009 | I143: 传说 | J143: 200 | K143: FALSE | L143: 消耗品盲盒产出 | M143: 0 | O143: v1\Treat\WhiskyCagar.png | P143: v1\ItemIcon\Treat_WhiskyCagar.png | R143: 一些国家不允许饮酒，替换成水 | S143: 109011 | T143: Item | V143: TRUE | W143: FALSE | X143: FALSE | Y143: TRUE | Z143: FALSE
B144: 10001 | C144: Basic Card Back | D144: 基础背 | E144: CardBack | F144: Playtest|Release|Demo | I144: 普通 | J144: 300 | K144: TRUE | L144: 初始拥有 | M144: 0 | O144: v1\CardBack\Basic.png | P144: v1\ItemIcon\CardBack_Basic.png | S144: 110001 | T144: Item | V144: TRUE | W144: FALSE | X144: FALSE | Y144: FALSE | Z144: FALSE
B145: 11001 | C145: Kibble Card Face | D145: 狗粮卡面 | E145: CardFace | F145: Playtest|Release|Demo | I145: 普通 | J145: 300 | K145: TRUE | L145: 初始拥有 | M145: 0 | O145: v1\CardFace\Classic\ | P145: v1\ItemIcon\CardFace_Kibble.png | R145: 开发阶段先临时用经典卡面 | S145: 111001 | T145: Item | V145: TRUE | W145: FALSE | X145: FALSE | Y145: FALSE | Z145: FALSE
B146: 11002 | C146: Classic Card Face | D146: 经典卡面 | E146: CardFace | F146: Playtest|Release|Demo | H146: 11001 | I146: 普通 | J146: 300 | K146: TRUE | L146: 初始拥有 | M146: 0 | O146: v1\CardFace\Classic\ | P146: v1\ItemIcon\CardFace_Classic.png | S146: 111002 | T146: Item | V146: TRUE | W146: FALSE | X146: FALSE | Y146: FALSE | Z146: FALSE
B147: 12001 | C147: Anchor Tattoo | D147: 锚纹身 | E147: BodyDecoration | F147: Playtest|Release | I147: 稀有 | J147: 300 | K147: FALSE | L147: 装扮盲盒产出 | M147: 0 | O147: v1\Player\BodyDecoration\AnchorTattoo.png | P147: v1\ItemIcon\BodyDecoration_AnchorTattoo.png | S147: 112001 | T147: Item | V147: TRUE | W147: FALSE | X147: FALSE | Y147: FALSE | Z147: FALSE
B148: 12002 | C148: Hair | D148: 体毛 | E148: BodyDecoration | F148: Playtest|Release|Demo | I148: 优秀 | J148: 300 | K148: FALSE | L148: 装扮盲盒产出 | M148: 0 | O148: v1\Player\BodyDecoration\Hair.png | P148: v1\ItemIcon\BodyDecoration_Hair.png | S148: 112002 | T148: Item | V148: TRUE | W148: FALSE | X148: FALSE | Y148: FALSE | Z148: FALSE
B149: 51001 | C149: Cream Shiba Inu | D149: 胖白柴 | E149: Dog | F149: Playtest|Release | I149: 特殊1 | J149: 200 | K149: FALSE | L149: 活动产出 | M149: 0 | O149: v3\Shiba\Cream\ | P149: v3\ItemIcon\Dog_1003.png | Q149: 1003 | R149: 小红书 | S149: 151001 | T149: Item | V149: TRUE | W149: FALSE | X149: FALSE | Y149: FALSE | Z149: FALSE
B150: 52001 | C150: Angel Halo | D150: 天使光环 | E150: Headwear | F150: Playtest|Release | I150: 特殊1 | J150: 100 | K150: FALSE | L150: 活动产出 | M150: 0 | O150: v2\Headwear\Hole.png | P150: v2\ItemIcon\Headwear_Hole.png | R150: 推特 | S150: 152001 | T150: Item | V150: TRUE | W150: FALSE | X150: FALSE | Y150: FALSE | Z150: FALSE
A151: ## | B151: 53001墓碑 | C151: Angel Golden Monocle | D151: 金色单片镜 | E151: Eyewear | F151: Playtest|Release | I151: 特殊1 | J151: 0 | K151: TRUE | L151: 已下架 | M151: 0 | O151: v1\Eyewear\Monocle_golden.png | P151: v1\ItemIcon\Eyewear_Monocle_golden.png | S151: 153001 | T151: Item | V151: TRUE | W151: FALSE | X151: FALSE | Y151: FALSE | Z151: TRUE
B152: 92005 | C152: Hole | D152: 测试活动功能帽 | E152: Headwear | F152: Playtest|Release | I152: 特殊1 | J152: 100 | K152: FALSE | L152: 活动产出 | M152: 0 | O152: v2\Headwear\Hole.png | P152: v2\ItemIcon\Headwear_Hole.png | R152: 测试活动功能使用 | S152: 192005 | T152: Item | V152: TRUE | W152: FALSE | X152: FALSE | Y152: FALSE | Z152: FALSE
B153: 91012 | C153: Unshaven Sesame | D153: 绅士赤柴 | E153: Dog | F153: Playtest|Release | I153: 特殊1 | J153: 100 | K153: FALSE | L153: 活动产出 | M153: 0 | O153: v3\Shiba\Red\ | P153: v3\ItemIcon\Dog_1012.png | Q153: 1012 | R153: 测试活动功能使用 | S153: 191012 | T153: Item | V153: TRUE | W153: FALSE | X153: FALSE | Y153: FALSE | Z153: FALSE

Sheet 表说明
A1: 枚举用例
B2: Dog | C2: 小狗本体 | E2: Mythic | F2: 神话 | H2: ALL | I2: 全球 | J2: 1 | K2: 在全部国家隐藏 | O2: Default | P2: 默认
B3: Headwear | C3: 小狗头部装饰 | E3: Legendary | F3: 传说 | H3: SA | I3: 沙特阿拉伯 | J3: 2 | K3: Saudi Arabia赌博/宗教/酒精/色情/进化论 | O3: Serious | P3: 严肃
B4: Eyewear | C4: 小狗眼部装饰 | E4: Epic | F4: 史诗 | H4: AE | I4: 阿联酋 | J4: 4 | K4: United Arab Emirates赌博/宗教/酒精/色情 | O4: Bored | P4: 无聊
B5: Arm | C5: 手臂层的装饰 | E5: Rare | F5: 稀有 | H5: IR | I5: 伊朗 | J5: 8 | K5: Iran宗教/进化论/赌博/政治/西方文化 | O5: Wink | P5: 媚眼
B6: Clothes | C6: 玩家手臂衣服 | E6: Uncommon | F6: 优秀 | H6: PK | I6: 巴基斯坦 | J6: 16 | K6: Pakistan国家形象/政治 | O6: Excited | P6: 兴奋
B7: Table | C7: 桌布 | E7: Common | F7: 普通 | H7: MY | I7: 马来西亚 | J7: 32 | K7: Malaysia赌博/暴力/LGBTQ/酒精 | O7: Starstruck | P7: 崇拜
B8: Background | C8: 背景 | E8: Special1 | F8: 特殊1 | H8: ID | I8: 印尼 | J8: 64 | K8: Indonesia赌博/暴力/LGBTQ/酒精 | O8: Silent | P8: 沉默
B9: Accessory | C9: 玩家手部装饰 | E9: Special2 | F9: 特殊2 | H9: RU | I9: 俄罗斯 | J9: 128 | K9: Russia赌博/LGBTQ/极端主义 | O9: Reject | P9: 拒绝
B10: Refreshment | C10: 消耗品 | H10: CN | I10: 中国 | J10: 256 | K10: China赌博/暴力/血腥/色情
B11: CardBack | C11: 卡背 | H11: KP | I11: 朝鲜 | J11: 512 | K11: North Korea国际制裁/政治
B12: CardFace | C12: 卡面 | H12: SY | I12: 叙利亚 | J12: 1024 | K12: Syria国际制裁/政治/宗教
B13: BodyDecoration | C13: 体表装饰 | H13: CU | I13: 古巴 | J13: 2048 | K13: Cuba国际制裁/政治
B18: Initial | C18: 初始拥有
B19: DecorationBlindBox | C19: 装扮盲盒产出
B20: RefreshmentBlindBox | C20: 消耗品盲盒产出
B21: EventReward | C21: 活动产出
B22: Retired | C22: 已下架
B23: DebugOnly | C23: 仅调试
A32: SteamItemDef ID段分配
A34: 分段 | B34: 100000-199999，1是给其分配的头，后面5位对应Item.id，规定 Item.Id <= 99999，并由转换器校验，正式 Item：SteamItemDefId = 100000 + Item.Id。Playtest 专用 Item 可以改用 410000-499999，不受该映射公式约束。
A35: 用途 | B35: 玩家实际拥有的内容物品
A36: 示例 | B36: 101xxx 狗皮肤、102xxx 头饰、103xxx 眼镜
A38: 分段 | B38: 200000-299999
A39: 用途 | B39: 可堆叠消耗品，例如盲盒券（开箱成本）、材料，通常放在玩家的Steam库存里，等待被玩家消耗
A40: 细分 | B40: 201000-229999，应当与盲盒有所一一对应，SteamOpenCostItemDefId = 200000 + BlindBox.Id，采用该映射的 BlindBox.Id 必须为 1-29999，并由转换器校验。
A41: 示例 | B41: 1001标准盲盒的盲盒券ID应当为201001
A42: 细分 | B42: 230xxx 分配给后续内容，例如熔炼助燃剂材料
A44: 分段 | B44: 300000-399999，可能不会和盲盒一一对应，多种途径都可以开启相同的权重随机池
A45: 用途 | B45: 权重随机物品生成器，Generator、交换产物定义
A46: 示例 | B46: 301xxx 盲盒 Generator、302xxx 熔炼 Generator
A48: 分段 | B48: 400000-499999，仅输出到 Playtest，不得进入 Release schema。转换器以后要同时检查 SteamItemDef 和 Item.SteamItemDefId，因为测试物品也可能来自 Item 表。
... A77: 用途 | B77: 暂不使用，作为低位保留段。

Sheet BlindBox
A1: ##var | B1: Id | C1: Name | D1: BuildChannelMask | E1: BoxType | F1: RewardSelectionMode | G1: DisplayMode | H1: CostChips | I1: HintValueMode | J1: MaxRevealClickCount | K1: AutoCollectSeconds | L1: HintIconPath | M1: IsPlatformInventoryRequired | N1: IsEnabled
A2: ##type | B2: int | C2: string | D2: EBuildChannelMask | E2: EBlindBoxType | F2: ERewardSelectionMode | G2: EBlindBoxDisplayMode | H2: int | I2: EBlindBoxValueMode | J2: int | K2: float | L2: string | M2: bool | N2: bool
A3: ## | B3: BlindBox.Id <= 29999 | C3: 策划/显示名称 | E3: 盲盒的奖励内容类别。用于约束奖池物品的投放类型；具体候选物品及权重由 BlindBoxItemWeight 按 BlindBoxId 配置。 | F3: 决定盲盒从自身奖池中选择奖励时，是否排除该盲盒此前已经抽中的物品。 | G3: 升级表演/直接展示 | H3: 基础固定价格，实际需乘以Config表里的倍率来使用 | J3: 装扮盲盒默认 3 | K3: 奖励展示后几秒自动收起 | L3: 图标路径 | M3: 装扮 true，消耗品 false 是必须使用当前平台的可信库存服务器 | N3: 临时开关
A4: ## | B4: 奖励盒ID | C4: 奖励盒名称 | D4: 适用构建渠道 | E4: 奖励盒类型 | F4: 奖励选择模式 | G4: 展示方式 | H4: 消耗筹码 | I4: 提示文字模式 | J4: 最大揭晓点击次数 | K4: 自动收起秒数 | L4: 图标路径 | M4: 是否需要服务器 | N4: 是否启用
B5: 1001 | C5: 标准盲盒 | D5: Playtest|Release | E5: 装扮盲盒 | F5: Normal | G5: 三次升级表演 | H5: 1000 | I5: Chips | J5: 3 | K5: 5 | L5: UI\BlindBox\HintIcon_Common.png | M5: TRUE | N5: TRUE
B6: 1002 | C6: 新手盲盒 | D6: Playtest|Release | E6: 新手装扮盲盒 | F6: Normal | G6: 三次升级表演 | H6: 1000 | I6: Chips | J6: 3 | K6: 5 | L6: UI\BlindBox\HintIcon_Common.png | M6: TRUE | N6: TRUE
B7: 2001 | C7: 消耗品盲盒 | D7: Playtest|Release | E7: 消耗品盲盒 | F7: Normal | G7: 三次升级表演 | H7: 1000 | I7: Chips | J7: 3 | K7: 5 | L7: UI\BlindBox\HintIcon_Common.png | M7: FALSE | N7: TRUE
B8: 2002 | C8: DEMO本地普通盲盒 | D8: Demo | E8: 装扮盲盒 | F8: ExcludeDrawnInThisBox | G8: 三次升级表演 | H8: 100 | I8: Chips | J8: 3 | K8: 5 | L8: UI\BlindBox\HintIcon_Common.png | M8: FALSE | N8: TRUE
B9: 2003 | C9: DEMO本地好奖励盲盒 | D9: Demo | E9: 装扮盲盒 | F9: ExcludeDrawnInThisBox | G9: 三次升级表演 | H9: 100 | I9: Chips | J9: 3 | K9: 5 | L9: UI\BlindBox\HintIcon_Common.png | M9: FALSE | N9: TRUE
B10: 3001 | C10: 测试活动盲盒 | D10: Playtest | E10: 活动盲盒 | F10: Normal | G10: 直接展示奖励 | H10: 0 | I10: Count | J10: 0 | K10: 5 | L10: UI\BlindBox\HintIcon_Common.png | M10: TRUE | N10: FALSE
B11: 4001 | C11: Old盲盒招待券专用（归档） | E11: 装扮盲盒 | F11: Normal | G11: 三次升级表演 | H11: 0 | I11: Count | J11: 3 | K11: 5 | L11: UI\BlindBox\HintIcon_Common_Ticket.png | M11: TRUE | N11: FALSE
B12: 4002 | C12: 录屏专用盲盒 | D12: PlaytestRecording | E12: 装扮盲盒 | F12: RecordingSequence | G12: 三次升级表演 | H12: 1000 | I12: Chips | J12: 3 | K12: 5 | L12: UI\BlindBox\HintIcon_Common.png | M12: FALSE | N12: TRUE

Sheet BlindBoxSchedule
A1: ##var | B1: Id | C1: NextScheduleId | D1: ProgressCheckpoint | E1: BuildChannelMask | F1: BlindBoxId | G1: FallbackBlindBoxId | H1: IsLoopTrack | I1: StartSeconds | J1: IntervalSeconds | N1: MaxGrantCount | O1: IsEnabled | P1: SteamPlaytimeGeneratorItemDefId | Q1: SteamDropIntervalSeconds | R1: SteamDropWindowSeconds | S1: SteamDropMaxPerWindow | U1: CostChipsOverride | V1: SteamCompletionReceiptItemDefId
A2: ##type | B2: int | C2: int | D2: int | E2: EBuildChannelMask | F2: int | G2: int | H2: bool | I2: int | J2: int | N2: int | O2: bool | P2: int | Q2: int | R2: int | S2: int | U2: int | V2: int
A3: ## | C3: 首轮奖励序列中，当前 Schedule 完成后进入的下一条 BlindBoxSchedule.Id；末条首轮 Schedule 填 0，循环 Schedule 填 0；所有启用的首轮 Schedule 必须组成无环、无分叉的单链，顺序不再根据 StartSeconds 或数字 ID 推断。 | D3: 当前 Schedule 正式完成后写入 Steam Stat 的只增进度值；仅首轮奖励序列填写大于 0，循环 Schedule 填 0；沿 NextScheduleId 必须严格递增，发布后不得修改、降低或复用；建议步骤之间预留较大数值间隔，方便以后插入步骤。 | F3: 对应 BlindBox.Id | G3: FallbackBlindBoxId | H3: TRUE 表示正常阶段循环装扮奖励准备行 | I3: 客户端用时间，负责展示气球，以及后台提前准备奖励 | J3: 非循环行为相对上次领取间隔；循环行为 Steam 直接奖励掉落间隔 | K3: 辅助计算列 | L3: 辅助计算列 | M3: 时间倍率；与基础间隔时间 | N3: 最多发放次数；不限填 -1 | O3: 是否启用 | P3: 通过 TriggerItemDrop 请求的 Steam PlaytimeGenerator ItemDef ID；该定义直接生成最终装扮；本地消耗品填 0 | Q3: 当前 PlaytimeGenerator 被预热激活后，正式获得一件奖励所需的 Steam 有效游玩秒数。 | R3: Steam 掉落窗口真实秒数；转换器向上取整为分钟；0 表示不启用 | S3: Steam 掉落窗口内最多发放次数；未启用窗口时填 0 | U3: >0 本次展示覆盖 BlindBox 默认筹码成本；=0 表示继承，<0 表示免费并显示其绝对值的字符串并添加删除线，注意配置中的倍率 | V3: 玩家正式完成并结算该 Schedule 后，由客户端手动授予的 Steam 永久进度回执 ItemDef ID；0 表示不授予
A4: ## | B4: 调度ID | C4: 后置调度 ID | D4: 序列进度值 | F4: 奖励盒ID | G4: 兜底盲盒id | H4: 是循环生效的 | I4: 开始秒数 | J4: 间隔秒数 | K4: 分钟 | L4: 累计分钟 | M4: 10 | N4: 最多发放次数 | O4: 是否启用 | P4: Steam游玩时间生成器DefID | Q4: 冷却窗口 | R4: Steam掉落窗口秒数 | S4: Steam窗口最大发放数 | U4: 本次筹码成本覆盖 | V4: Steam完成回执DefID
B5: 1001 | C5: 1002 | D5: 1000 | E5: Playtest|Release | F5: 1001 | G5: 2001 | H5: FALSE | I5: =SUM($J$5:J5) -> 300 | J5: =M5*$M$4 -> 300 | K5: =J5/60 -> 5 | L5: =SUM($K$5:K5) -> 5 | M5: 30 | N5: 1 | O5: TRUE | P5: 700101 | Q5: 120 | R5: 0 | S5: 0 | U5: -1000 | V5: 0
B6: 1002 | C6: 1003 | D6: 2000 | E6: Playtest|Release | F6: 1002 | G6: 2001 | H6: FALSE | I6: =SUM($J$5:J6) -> 660 | J6: =M6*$M$4 -> 360 | K6: =J6/60 -> 6 | L6: =SUM($K$5:K6) -> 11 | M6: 36 | N6: 1 | O6: TRUE | P6: 700102 | Q6: 120 | R6: 0 | S6: 0 | U6: 0 | V6: 0
B7: 1003 | C7: 1004 | D7: 3000 | E7: Playtest|Release | F7: 2001 | H7: FALSE | I7: =SUM($J$5:J7) -> 1140 | J7: =M7*$M$4 -> 480 | K7: =J7/60 -> 8 | L7: =SUM($K$5:K7) -> 19 | M7: 48 | N7: 1 | O7: TRUE | P7: 0 | Q7: 0 | R7: 0 | S7: 0 | U7: 0 | V7: 0
B8: 1004 | C8: 1005 | D8: 4000 | E8: Playtest|Release | F8: 1001 | G8: 2001 | H8: FALSE | I8: =SUM($J$5:J8) -> 1620 | J8: =M8*$M$4 -> 480 | K8: =J8/60 -> 8 | L8: =SUM($K$5:K8) -> 27 | M8: 48 | N8: 1 | O8: TRUE | P8: 700104 | Q8: 120 | R8: 0 | S8: 0 | U8: 0 | V8: 0
B9: 1005 | C9: 1006 | D9: 5000 | E9: Playtest|Release | F9: 1002 | G9: 2001 | H9: FALSE | I9: =SUM($J$5:J9) -> 2220 | J9: =M9*$M$4 -> 600 | K9: =J9/60 -> 10 | L9: =SUM($K$5:K9) -> 37 | M9: 60 | N9: 1 | O9: TRUE | P9: 700105 | Q9: 120 | R9: 0 | S9: 0 | U9: 0 | V9: 500005
B10: 1006 | C10: 1007 | D10: 6000 | E10: Playtest|Release | F10: 2001 | H10: FALSE | I10: =SUM($J$5:J10) -> 2820 | J10: =M10*$M$4 -> 600 | K10: =J10/60 -> 10 | L10: =SUM($K$5:K10) -> 47 | M10: 60 | N10: 1 | O10: TRUE | P10: 0 | Q10: 0 | R10: 0 | S10: 0 | U10: 0 | V10: 0
B11: 1007 | C11: 1008 | D11: 7000 | E11: Playtest|Release | F11: 1001 | G11: 2001 | H11: FALSE | I11: =SUM($J$5:J11) -> 3540 | J11: =M11*$M$4 -> 720 | K11: =J11/60 -> 12 | L11: =SUM($K$5:K11) -> 59 | M11: 72 | N11: 1 | O11: TRUE | P11: 700107 | Q11: 120 | R11: 0 | S11: 0 | U11: 0 | V11: 0
B12: 1008 | C12: 1009 | D12: 8000 | E12: Playtest|Release | F12: 1002 | G12: 2001 | H12: FALSE | I12: =SUM($J$5:J12) -> 4260 | J12: =M12*$M$4 -> 720 | K12: =J12/60 -> 12 | L12: =SUM($K$5:K12) -> 71 | M12: 72 | N12: 1 | O12: TRUE | P12: 700108 | Q12: 120 | R12: 0 | S12: 0 | U12: 0 | V12: 0
B13: 1009 | C13: 1010 | D13: 9000 | E13: Playtest|Release | F13: 2001 | H13: FALSE | I13: =SUM($J$5:J13) -> 5160 | J13: =M13*$M$4 -> 900 | K13: =J13/60 -> 15 | L13: =SUM($K$5:K13) -> 86 | M13: 90 | N13: 1 | O13: TRUE | P13: 0 | Q13: 0 | R13: 0 | S13: 0 | U13: 0 | V13: 0
B14: 1010 | C14: 1011 | D14: 10000 | E14: Playtest|Release | F14: 1001 | G14: 2001 | H14: FALSE | I14: =SUM($J$5:J14) -> 6060 | J14: =M14*$M$4 -> 900 | K14: =J14/60 -> 15 | L14: =SUM($K$5:K14) -> 101 | M14: 90 | N14: 1 | O14: TRUE | P14: 700110 | Q14: 120 | R14: 0 | S14: 0 | U14: 0 | V14: 0
B15: 1011 | C15: 1012 | D15: 11000 | E15: Playtest|Release | F15: 1002 | G15: 2001 | H15: FALSE | I15: =SUM($J$5:J15) -> 6960 | J15: =M15*$M$4 -> 900 | K15: =J15/60 -> 15 | L15: =SUM($K$5:K15) -> 116 | M15: 90 | N15: 1 | O15: TRUE | P15: 700111 | Q15: 120 | R15: 0 | S15: 0 | U15: 0 | V15: 0
B16: 1012 | C16: 0 | D16: 12000 | E16: Playtest|Release | F16: 2001 | H16: FALSE | I16: =SUM($J$5:J16) -> 7860 | J16: =M16*$M$4 -> 900 | K16: =J16/60 -> 15 | L16: =SUM($K$5:K16) -> 131 | M16: 90 | N16: 1 | O16: TRUE | P16: 0 | Q16: 0 | R16: 0 | S16: 0 | U16: 0 | V16: 500012
A17: ##
B18: 2001 | C18: 0 | D18: 0 | E18: Playtest|Release | F18: 1001 | G18: 2001 | H18: TRUE | J18: =90*$M$4 -> 900 | N18: -1 | O18: TRUE | P18: 701101 | Q18: =180*$M$4 -> 1800 | R18: =360*$M$4 -> 3600 | S18: 2 | U18: 0 | V18: 0
A19: ## | M19: 10
B20: 3001 | C20: 3002 | D20: 1000 | E20: Demo | F20: 2002 | G20: 0 | H20: FALSE | I20: =SUM($J$20:J20) -> 60 | J20: =M20*$M$19 -> 60 | K20: =J20/60 -> 1 | L20: =SUM($K$20:K20) -> 1 | M20: 6 | N20: 1 | O20: TRUE | P20: 0 | Q20: 0 | R20: 0 | S20: 0 | U20: 0 | V20: 0
B21: 3002 | C21: 3003 | D21: 2000 | E21: Demo | F21: 2003 | G21: 0 | H21: FALSE | I21: =SUM($J$20:J21) -> 120 | J21: =M21*$M$19 -> 60 | K21: =J21/60 -> 1 | L21: =SUM($K$20:K21) -> 2 | M21: 6 | N21: 1 | O21: TRUE | P21: 0 | Q21: 0 | R21: 0 | S21: 0 | U21: 0 | V21: 0
B22: 3003 | C22: 3004 | D22: 3000 | E22: Demo | F22: 2003 | G22: 0 | H22: FALSE | I22: =SUM($J$20:J22) -> 180 | J22: =M22*$M$19 -> 60 | K22: =J22/60 -> 1 | L22: =SUM($K$20:K22) -> 3 | M22: 6 | N22: 1 | O22: TRUE | P22: 0 | Q22: 0 | R22: 0 | S22: 0 | U22: 0 | V22: 0
B23: 3004 | C23: 3005 | D23: 4000 | E23: Demo | F23: 2002 | G23: 0 | H23: FALSE | I23: =SUM($J$20:J23) -> 270 | J23: =M23*$M$19 -> 90 | K23: =J23/60 -> 1.5 | L23: =SUM($K$20:K23) -> 4.5 | M23: 9 | N23: 1 | O23: TRUE | P23: 0 | Q23: 0 | R23: 0 | S23: 0 | U23: 0 | V23: 0
B24: 3005 | C24: 3006 | D24: 5000 | E24: Demo | F24: 2002 | G24: 0 | H24: FALSE | I24: =SUM($J$20:J24) -> 360 | J24: =M24*$M$19 -> 90 | K24: =J24/60 -> 1.5 | L24: =SUM($K$20:K24) -> 6 | M24: 9 | N24: 1 | O24: TRUE | P24: 0 | Q24: 0 | R24: 0 | S24: 0 | U24: 0 | V24: 0
B25: 3006 | C25: 3007 | D25: 6000 | E25: Demo | F25: 2002 | G25: 0 | H25: FALSE | I25: =SUM($J$20:J25) -> 480 | J25: =M25*$M$19 -> 120 | K25: =J25/60 -> 2 | L25: =SUM($K$20:K25) -> 8 | M25: 12 | N25: 1 | O25: TRUE | P25: 0 | Q25: 0 | R25: 0 | S25: 0 | U25: 0 | V25: 0
B26: 3007 | C26: 3008 | D26: 7000 | E26: Demo | F26: 2002 | G26: 0 | H26: FALSE | I26: =SUM($J$20:J26) -> 600 | J26: =M26*$M$19 -> 120 | K26: =J26/60 -> 2 | L26: =SUM($K$20:K26) -> 10 | M26: 12 | N26: 1 | O26: TRUE | P26: 0 | Q26: 0 | R26: 0 | S26: 0 | U26: 0 | V26: 0
B27: 3008 | C27: 3009 | D27: 8000 | E27: Demo | F27: 2003 | G27: 0 | H27: FALSE | I27: =SUM($J$20:J27) -> 750 | J27: =M27*$M$19 -> 150 | K27: =J27/60 -> 2.5 | L27: =SUM($K$20:K27) -> 12.5 | M27: 15 | N27: 1 | O27: TRUE | P27: 0 | Q27: 0 | R27: 0 | S27: 0 | U27: 0 | V27: 0
B28: 3009 | C28: 3010 | D28: 9000 | E28: Demo | F28: 2002 | G28: 0 | H28: FALSE | I28: =SUM($J$20:J28) -> 900 | J28: =M28*$M$19 -> 150 | K28: =J28/60 -> 2.5 | L28: =SUM($K$20:K28) -> 15 | M28: 15 | N28: 1 | O28: TRUE | P28: 0 | Q28: 0 | R28: 0 | S28: 0 | U28: 0 | V28: 0
B29: 3010 | C29: 3011 | D29: 10000 | E29: Demo | F29: 2002 | G29: 0 | H29: FALSE | I29: =SUM($J$20:J29) -> 1080 | J29: =M29*$M$19 -> 180 | K29: =J29/60 -> 3 | L29: =SUM($K$20:K29) -> 18 | M29: 18 | N29: 1 | O29: TRUE | P29: 0 | Q29: 0 | R29: 0 | S29: 0 | U29: 0 | V29: 0
B30: 3011 | C30: 3012 | D30: 11000 | E30: Demo | F30: 2002 | G30: 0 | H30: FALSE | I30: =SUM($J$20:J30) -> 1260 | J30: =M30*$M$19 -> 180 | K30: =J30/60 -> 3 | L30: =SUM($K$20:K30) -> 21 | M30: 18 | N30: 1 | O30: TRUE | P30: 0 | Q30: 0 | R30: 0 | S30: 0 | U30: 0 | V30: 0
B31: 3012 | C31: 3013 | D31: 12000 | E31: Demo | F31: 2002 | G31: 0 | H31: FALSE | I31: =SUM($J$20:J31) -> 1470 | J31: =M31*$M$19 -> 210 | K31: =J31/60 -> 3.5 | L31: =SUM($K$20:K31) -> 24.5 | M31: 21 | N31: 1 | O31: TRUE | P31: 0 | Q31: 0 | R31: 0 | S31: 0 | U31: 0 | V31: 0
... B34: 3015 | C34: 0 | D34: 15000 | E34: Demo | F34: 2002 | G34: 0 | H34: FALSE | I34: =SUM($J$20:J34) -> 2220 | J34: =M34*$M$19 -> 300 | K34: =J34/60 -> 5 | L34: =SUM($K$20:K34) -> 37 | M34: 30 | N34: 1 | O34: TRUE | P34: 0 | Q34: 0 | R34: 0 | S34: 0 | U34: 0 | V34: 0
A35: ##
B36: 4001 | C36: 0 | D36: 0 | E36: PlaytestRecording | F36: 4002 | G36: 0 | H36: TRUE | J36: 5 | N36: -1 | O36: TRUE | P36: 0 | Q36: 0 | R36: 0 | S36: 0 | U36: 1000 | V36: 0

Sheet BlindBoxRarityRate
A1: ##var | B1: Id | C1: BlindBoxId | D1: Rarity | E1: Weight | G1: IsEnabled
A2: ##type | B2: int | C2: int | D2: ERarity | E2: int | G2: bool
A3: ## | B3: id无实际意义01与稀有读无关 | C3: 对应 BlindBox.Id | D3: 先抽品质时命中的品质 | E3: 品质权重，0 或禁用表示不参与 | G3: 是否启用
A4: ## | B4: id | C4: 奖励盒ID | D4: 品质 | E4: 权重 | G4: 是否启用 | H4: 备注
B5: 100101 | C5: 1001 | D5: 普通 | E5: 0 | F5: =E5/10000 -> 0 | G5: TRUE
B6: 100102 | C6: 1001 | D6: 优秀 | E6: 6700 | F6: =E6/10000 -> 0.67 | G6: TRUE
B7: 100103 | C7: 1001 | D7: 稀有 | E7: 2200 | F7: =E7/10000 -> 0.22 | G7: TRUE
B8: 100104 | C8: 1001 | D8: 史诗 | E8: 900 | F8: =E8/10000 -> 0.09 | G8: TRUE
B9: 100105 | C9: 1001 | D9: 传说 | E9: 180 | F9: =E9/10000 -> 0.018 | G9: TRUE
B10: 100106 | C10: 1001 | D10: 神话 | E10: 20 | F10: =E10/10000 -> 0.002 | G10: TRUE
A11: ## | F11: =SUM(F5:F10) -> 1
B12: 100201 | C12: 1002 | D12: 普通 | E12: 0 | F12: =E12/10000 -> 0 | G12: TRUE
B13: 100202 | C13: 1002 | D13: 优秀 | E13: 3700 | F13: =E13/10000 -> 0.37 | G13: TRUE | H13: 新手盲盒概率会高一点
B14: 100203 | C14: 1002 | D14: 稀有 | E14: 4200 | F14: =E14/10000 -> 0.42 | G14: TRUE
B15: 100204 | C15: 1002 | D15: 史诗 | E15: 1700 | F15: =E15/10000 -> 0.17 | G15: TRUE
B16: 100205 | C16: 1002 | D16: 传说 | E16: 380 | F16: =E16/10000 -> 0.038 | G16: TRUE
B17: 100206 | C17: 1002 | D17: 神话 | E17: 20 | F17: =E17/10000 -> 0.002 | G17: TRUE
A18: ## | F18: =SUM(F12:F17) -> 1
B19: 200101 | C19: 2001 | D19: 普通 | E19: 0 | F19: =E19/10000 -> 0 | G19: TRUE | H19: 消耗品
B20: 200102 | C20: 2001 | D20: 优秀 | E20: 3000 | F20: =E20/10000 -> 0.3 | G20: TRUE | H20: 消耗品
B21: 200103 | C21: 2001 | D21: 稀有 | E21: 5000 | F21: =E21/10000 -> 0.5 | G21: TRUE | H21: 消耗品
B22: 200104 | C22: 2001 | D22: 史诗 | E22: 1700 | F22: =E22/10000 -> 0.17 | G22: TRUE | H22: 消耗品
B23: 200105 | C23: 2001 | D23: 传说 | E23: 380 | F23: =E23/10000 -> 0.038 | G23: TRUE | H23: 消耗品
B24: 200106 | C24: 2001 | D24: 神话 | E24: 0 | F24: =E24/10000 -> 0 | G24: TRUE | H24: 消耗品
A25: ## | F25: =SUM(F19:F24) -> 1.008
B26: 200201 | C26: 2002 | D26: 普通 | E26: 0 | F26: =E26/10000 -> 0 | G26: TRUE | H26: Demo盲盒普
B27: 200202 | C27: 2002 | D27: 优秀 | E27: 3700 | F27: =E27/10000 -> 0.37 | G27: TRUE | H27: Demo盲盒普
B28: 200203 | C28: 2002 | D28: 稀有 | E28: 4200 | F28: =E28/10000 -> 0.42 | G28: TRUE | H28: Demo盲盒普
B29: 200204 | C29: 2002 | D29: 史诗 | E29: 1700 | F29: =E29/10000 -> 0.17 | G29: TRUE | H29: Demo盲盒普
B30: 200205 | C30: 2002 | D30: 传说 | E30: 0 | F30: =E30/10000 -> 0 | G30: TRUE | H30: Demo盲盒普
B31: 200206 | C31: 2002 | D31: 神话 | E31: 0 | F31: =E31/10000 -> 0 | G31: TRUE | H31: Demo盲盒普
A32: ## | F32: =SUM(F26:F31) -> 0.96
B33: 200301 | C33: 2003 | D33: 普通 | E33: 0 | F33: =E33/SUM($E$33:$E$38) -> 0 | G33: TRUE | H33: Demo盲盒狗
B34: 200302 | C34: 2003 | D34: 优秀 | E34: 0 | F34: =E34/SUM($E$33:$E$38) -> 0 | G34: TRUE | H34: Demo盲盒狗
B35: 200303 | C35: 2003 | D35: 稀有 | E35: 0 | F35: =E35/SUM($E$33:$E$38) -> 0 | G35: TRUE | H35: Demo盲盒狗
B36: 200304 | C36: 2003 | D36: 史诗 | E36: 1000 | F36: =E36/SUM($E$33:$E$38) -> 0.43478261 | G36: TRUE | H36: Demo盲盒狗
B37: 200305 | C37: 2003 | D37: 传说 | E37: 800 | F37: =E37/SUM($E$33:$E$38) -> 0.34782609 | G37: TRUE | H37: Demo盲盒狗
B38: 200306 | C38: 2003 | D38: 神话 | E38: 500 | F38: =E38/SUM($E$33:$E$38) -> 0.2173913 | G38: TRUE | H38: Demo盲盒狗
A39: ## | F39: =SUM(F33:F38) -> 1
B40: 300101 | C40: 3001 | D40: 特殊1 | E40: 100 | G40: FALSE | H40: 测试活动盲盒：特殊1
A41: ##
B42: 400101 | C42: 4001 | D42: 普通 | E42: 0 | F42: =E42/10000 -> 0 | G42: TRUE | H42: 盲盒券
B43: 400102 | C43: 4001 | D43: 优秀 | E43: 6700 | F43: =E43/10000 -> 0.67 | G43: TRUE
B44: 400103 | C44: 4001 | D44: 稀有 | E44: 2200 | F44: =E44/10000 -> 0.22 | G44: TRUE
B45: 400104 | C45: 4001 | D45: 史诗 | E45: 900 | F45: =E45/10000 -> 0.09 | G45: TRUE
B46: 400105 | C46: 4001 | D46: 传说 | E46: 180 | F46: =E46/10000 -> 0.018 | G46: TRUE
B47: 400106 | C47: 4001 | D47: 神话 | E47: 20 | F47: =E47/10000 -> 0.002 | G47: TRUE
A48: ## | F48: =SUM(F42:F47) -> 1
B49: 400201 | C49: 4002 | D49: 普通 | E49: 100 | F49: =E49/10000 -> 0.01 | G49: TRUE | H49: 录屏用
B50: 400202 | C50: 4002 | D50: 优秀 | E50: 100 | F50: =E50/10000 -> 0.01 | G50: TRUE
B51: 400203 | C51: 4002 | D51: 稀有 | E51: 100 | F51: =E51/10000 -> 0.01 | G51: TRUE
B52: 400204 | C52: 4002 | D52: 史诗 | E52: 100 | F52: =E52/10000 -> 0.01 | G52: TRUE
B53: 400205 | C53: 4002 | D53: 传说 | E53: 100 | F53: =E53/10000 -> 0.01 | G53: TRUE
B54: 400206 | C54: 4002 | D54: 神话 | E54: 100 | F54: =E54/10000 -> 0.01 | G54: TRUE
F55: =SUM(F49:F54) -> 0.06

Sheet BlindBoxItemWeight
A1: ##var | B1: Id | C1: BlindBoxId | D1: ItemId | E1: Weight | F1: IsEnabled | G1: RecordingRewardOrder
A2: ##type | B2: int | C2: int | D2: int | E2: int | F2: bool | G2: int
A3: ## | B3: 稳定且唯一的行ID | C3: 对应 BlindBox.Id | D3: 对应 Item.Id | E3: 同一盲盒、同一品质内的物品相对权重 | F3: 关闭后不参与奖池，但保留权重 | G3: 仅顺序发奖模式使用。0 不加入队列；正整数按升序发奖，同一盲盒内不可重复；走到末尾后循环。
A4: ## | B4: id | C4: 奖励盒ID | D4: 物品ID | E4: 物品权重 | F4: 是否启用 | G4: RecordingRewardOrder | H4: 备注 | I4: 备注
B5: 100101002 | C5: 1001 | D5: 1002 | E5: 300 | F5: TRUE | H5: 标准盲盒
B6: 100101003 | C6: 1001 | D6: 1003 | E6: 90 | F6: TRUE | H6: 标准盲盒
B7: 100101004 | C7: 1001 | D7: 1004 | E7: 90 | F7: TRUE | H7: 标准盲盒
B8: 100101005 | C8: 1001 | D8: 1005 | E8: 190 | F8: TRUE | H8: 标准盲盒
B9: 100101006 | C9: 1001 | D9: 1006 | E9: 150 | F9: TRUE | H9: 标准盲盒
B10: 100101007 | C10: 1001 | D10: 1007 | E10: 200 | F10: TRUE | H10: 标准盲盒
B11: 100101008 | C11: 1001 | D11: 1008 | E11: 2 | F11: TRUE | H11: 标准盲盒
B12: 100101009 | C12: 1001 | D12: 1009 | E12: 200 | F12: TRUE | H12: 标准盲盒
B13: 100101010 | C13: 1001 | D13: 1010 | E13: 150 | F13: TRUE | H13: 标准盲盒
B14: 100101011 | C14: 1001 | D14: 1011 | E14: 2 | F14: TRUE | H14: 标准盲盒
B15: 100101012 | C15: 1001 | D15: 1012 | E15: 200 | F15: TRUE | H15: 标准盲盒
B16: 100101013 | C16: 1001 | D16: 1013 | E16: 2 | F16: TRUE | H16: 标准盲盒
... B69: 100102029 | C69: 1001 | D69: 2029 | E69: 100 | F69: TRUE | H69: 标准盲盒
B70: =C70*100000+D70 -> 100102030 | C70: 1001 | D70: 2030 | E70: 100 | F70: TRUE | H70: 标准盲盒
B71: =C71*100000+D71 -> 100102031 | C71: 1001 | D71: 2031 | E71: 100 | F71: TRUE | H71: 标准盲盒
B72: =C72*100000+D72 -> 100102032 | C72: 1001 | D72: 2032 | E72: 100 | F72: TRUE | H72: 标准盲盒
B73: =C73*100000+D73 -> 100102033 | C73: 1001 | D73: 2033 | E73: 100 | F73: TRUE | H73: 标准盲盒
B74: =C74*100000+D74 -> 100105001 | C74: 1001 | D74: 5001 | E74: 100 | F74: TRUE | H74: 标准盲盒
B75: =C75*100000+D75 -> 100105002 | C75: 1001 | D75: 5002 | E75: 100 | F75: TRUE | H75: 标准盲盒
B76: =C76*100000+D76 -> 100105003 | C76: 1001 | D76: 5003 | E76: 100 | F76: TRUE | H76: 标准盲盒
B77: =C77*100000+D77 -> 100105004 | C77: 1001 | D77: 5004 | E77: 100 | F77: TRUE | H77: 标准盲盒
B78: =C78*100000+D78 -> 100105005 | C78: 1001 | D78: 5005 | E78: 100 | F78: TRUE | H78: 标准盲盒
B79: =C79*100000+D79 -> 100105006 | C79: 1001 | D79: 5006 | E79: 100 | F79: TRUE | H79: 标准盲盒
B80: =C80*100000+D80 -> 100105007 | C80: 1001 | D80: 5007 | E80: 100 | F80: TRUE | H80: 标准盲盒
B81: =C81*100000+D81 -> 100105008 | C81: 1001 | D81: 5008 | E81: 100 | F81: TRUE | H81: 标准盲盒
... B119: =C119*100000+D119 -> 100108012 | C119: 1001 | D119: 8012 | E119: 300 | F119: TRUE | H119: 标准盲盒
B120: 100108013 | C120: 1001 | D120: 8013 | E120: 200 | F120: TRUE | H120: 标准盲盒
B121: 100112001 | C121: 1001 | D121: 12001 | E121: 120 | F121: TRUE | H121: 标准盲盒
B122: 100112002 | C122: 1001 | D122: 12002 | E122: 120 | F122: TRUE | H122: 标准盲盒
B123: =C123*100000+D123 -> 100201002 | C123: 1002 | D123: 1002 | E123: 900 | F123: TRUE | H123: 新手盲盒
B124: =C124*100000+D124 -> 100201003 | C124: 1002 | D124: 1003 | E124: 90 | F124: TRUE | H124: 新手盲盒
B125: =C125*100000+D125 -> 100201004 | C125: 1002 | D125: 1004 | E125: 90 | F125: TRUE | H125: 新手盲盒
B126: =C126*100000+D126 -> 100201005 | C126: 1002 | D126: 1005 | E126: 190 | F126: TRUE | H126: 新手盲盒
B127: =C127*100000+D127 -> 100201006 | C127: 1002 | D127: 1006 | E127: 150 | F127: TRUE | H127: 新手盲盒
B128: =C128*100000+D128 -> 100201007 | C128: 1002 | D128: 1007 | E128: 200 | F128: TRUE | H128: 新手盲盒
B129: =C129*100000+D129 -> 100201008 | C129: 1002 | D129: 1008 | E129: 2 | F129: TRUE | H129: 新手盲盒
B130: =C130*100000+D130 -> 100201009 | C130: 1002 | D130: 1009 | E130: 200 | F130: TRUE | H130: 新手盲盒
B131: =C131*100000+D131 -> 100201010 | C131: 1002 | D131: 1010 | E131: 150 | F131: TRUE | H131: 新手盲盒
B132: =C132*100000+D132 -> 100201011 | C132: 1002 | D132: 1011 | E132: 2 | F132: TRUE | H132: 新手盲盒
B133: =C133*100000+D133 -> 100201012 | C133: 1002 | D133: 1012 | E133: 200 | F133: TRUE | H133: 新手盲盒
B134: =C134*100000+D134 -> 100201013 | C134: 1002 | D134: 1013 | E134: 2 | F134: TRUE | H134: 新手盲盒
... B267: =C267*100000+D267 -> 200301008 | C267: 2003 | D267: 1008 | E267: 100 | F267: TRUE | H267: Demo盲盒狗
B268: 200301011 | C268: 2003 | D268: 1011 | E268: 100 | F268: TRUE | H268: Demo盲盒狗
B269: 200301013 | C269: 2003 | D269: 1013 | E269: 100 | F269: TRUE | H269: Demo盲盒狗
B270: =C270*100000+D270 -> 200302013 | C270: 2003 | D270: 2013 | E270: 600 | F270: TRUE | H270: Demo盲盒狗
B271: =C271*100000+D271 -> 400202018 | C271: 4002 | D271: 2018 | E271: 100 | F271: TRUE | G271: 1
B272: =C272*100000+D272 -> 400201020 | C272: 4002 | D272: 1020 | E272: 100 | F272: TRUE | G272: 2
B273: =C273*100000+D273 -> 400202022 | C273: 4002 | D273: 2022 | E273: 100 | F273: TRUE | G273: 3
B274: =C274*100000+D274 -> 400202029 | C274: 4002 | D274: 2029 | E274: 100 | F274: TRUE | G274: 4

Sheet BlindBoxRevealPath
A1: ##var | B1: Id | C1: ActualRarity | D1: Weight | E1: StartRarity | F1: MiddleRarity1 | G1: MiddleRarity2 | H1: FinalRarity | I1: IsEnabled | J1: CanEndEarly
A2: ##type | B2: int | C2: ERarity | D2: int | E2: ERarity | F2: ERarity | G2: ERarity | H2: ERarity | I2: bool | J2: bool
A3: ## | C3: 抽奖结果的真实品质 | D3: 采用这条演出路径的权重 | E3: 盒子初始显示品质 | F3: 点击过程中的中间品质 | G3: 点击过程中的中间品质 | H3: 揭晓前最终显示品质 | I3: 是否启用 | J3: 达到最高品质后是否提前结束
A4: ## | B4: id | C4: 实际品质 | D4: 采用权重 | E4: 初始品质 | F4: 过程品质1 | G4: 过程品质1 | H4: 最终品质 | I4: 是否启用 | J4: 是否提前结束 | K4: 备注
B5: 100401 | C5: 普通 | D5: 100 | E5: 普通 | F5: 普通 | G5: 普通 | H5: 普通 | I5: TRUE | J5: TRUE
A6: ##
B7: 100501 | C7: 优秀 | D7: 45 | E7: 普通 | F7: 普通 | G7: 普通 | H7: 优秀 | I7: TRUE | J7: TRUE
B8: 100502 | C8: 优秀 | D8: 45 | E8: 普通 | F8: 普通 | G8: 优秀 | H8: 优秀 | I8: TRUE | J8: TRUE
B9: 100503 | C9: 优秀 | D9: 10 | E9: 普通 | F9: 优秀 | G9: 优秀 | H9: 优秀 | I9: TRUE | J9: TRUE
A10: ##
B11: 100601 | C11: 稀有 | D11: 45 | E11: 普通 | F11: 普通 | G11: 优秀 | H11: 稀有 | I11: TRUE | J11: TRUE
B12: 100602 | C12: 稀有 | D12: 25 | E12: 普通 | F12: 优秀 | G12: 优秀 | H12: 稀有 | I12: TRUE | J12: TRUE
B13: 100603 | C13: 稀有 | D13: 25 | E13: 普通 | F13: 优秀 | G13: 稀有 | H13: 稀有 | I13: TRUE | J13: TRUE
B14: 100604 | C14: 稀有 | D14: 5 | E14: 优秀 | F14: 稀有 | G14: 稀有 | H14: 稀有 | I14: TRUE | J14: TRUE
A15: ##
B16: 100701 | C16: 史诗 | D16: 65 | E16: 普通 | F16: 优秀 | G16: 稀有 | H16: 史诗 | I16: TRUE | J16: TRUE
B17: 100702 | C17: 史诗 | D17: 15 | E17: 普通 | F17: 稀有 | G17: 稀有 | H17: 史诗 | I17: TRUE | J17: TRUE | K17: 连升2
B18: 100703 | C18: 史诗 | D18: 15 | E18: 普通 | F18: 优秀 | G18: 优秀 | H18: 史诗 | I18: TRUE | J18: TRUE | K18: 连升2
B19: 100704 | C19: 史诗 | D19: 5 | E19: 优秀 | F19: 稀有 | G19: 史诗 | H19: 史诗 | I19: TRUE | J19: TRUE
A20: ##
B21: 100801 | C21: 传说 | D21: 37 | E21: 普通 | F21: 稀有 | G21: 史诗 | H21: 传说 | I21: TRUE | J21: TRUE | K21: 连升2
B22: 100802 | C22: 传说 | D22: 55 | E22: 普通 | F22: 优秀 | G22: 史诗 | H22: 传说 | I22: TRUE | J22: TRUE | K22: 连升2
B23: 100803 | C23: 传说 | D23: 3 | E23: 稀有 | F23: 史诗 | G23: 史诗 | H23: 传说 | I23: TRUE | J23: TRUE
B24: 100804 | C24: 传说 | D24: 5 | E24: 优秀 | F24: 稀有 | G24: 史诗 | H24: 传说 | I24: TRUE | J24: TRUE
A25: ##
B26: 100901 | C26: 神话 | D26: 25 | E26: 稀有 | F26: 史诗 | G26: 传说 | H26: 神话 | I26: TRUE | J26: TRUE
B27: 100902 | C27: 神话 | D27: 25 | E27: 稀有 | F27: 稀有 | G27: 传说 | H27: 神话 | I27: TRUE | J27: TRUE | K27: 连升2
B28: 100903 | C28: 神话 | D28: 25 | E28: 稀有 | F28: 传说 | G28: 传说 | H28: 神话 | I28: TRUE | J28: TRUE | K28: 连升2
B29: 100904 | C29: 神话 | D29: 25 | E29: 普通 | F29: 稀有 | G29: 传说 | H29: 神话 | I29: TRUE | J29: TRUE | K29: 连升2
A30: ##
B31: 200101 | C31: 特殊1 | D31: 100 | E31: 特殊1 | F31: 特殊1 | G31: 特殊1 | H31: 特殊1 | I31: FALSE | J31: TRUE
B32: 200201 | C32: 特殊2 | D32: 100 | E32: 特殊2 | F32: 特殊2 | G32: 特殊2 | H32: 特殊2 | I32: FALSE | J32: TRUE

Sheet BlindBoxVisual
A1: ##var | B1: Id | C1: Name | D1: ItemRarity | E1: BlindBoxSpritePath | F1: BlindBoxShadowPath | G1: BlindBoxGlowPath | H1: BlindBoxBackgroundColor | I1: BlindBoxBackgroundPath | K1: UpgradeSfxNamePath | L1: UpgradeEffectPath
A2: ##type | B2: int | C2: string | D2: ERarity | E2: string | F2: string | G2: string | H2: string | I2: string | K2: string | L2: string
A3: ## | C3: 显示名称不会显示在开盲盒环节，但如果游戏中有地方需要显示名字，例如Log，则使用该名字 | E3: 该品质盲盒主体图 | G3: 可选 | H3: 16进制颜色代码 | I3: 可选 | K3: 开盲盒环节，该品质出现时，播放的音效。 根据约定，音效在游戏后期配置，前期只在控制台打印文字即可。
A4: ## | B4: id | C4: 显示名称 | D4: 品质 | E4: 盲盒图片 | F4: 阴影图片 | G4: 盲盒发光图 | H4: 背景颜色 | I4: 盲盒背景图 | J4: 备注 | K4: 升品音效文件路径 | L4: 升品特效路径
B5: 1001 | C5: Mythic | D5: 神话 | E5: UI\BlindBox\BlindBox_Mythic_Closed.png | F5: UI\BlindBox\BlindBox_General_Shadow.png | H5: e3504a | K5: mi
B6: 1002 | C6: Legendary | D6: 传说 | E6: UI\BlindBox\BlindBox_Legendary_Closed.png | F6: UI\BlindBox\BlindBox_General_Shadow.png | H6: f0b811 | K6: do
B7: 1003 | C7: Epic | D7: 史诗 | E7: UI\BlindBox\BlindBox_Epic_Closed.png | F7: UI\BlindBox\BlindBox_General_Shadow.png | H7: b574f0 | K7: si
B8: 1004 | C8: Rare | D8: 稀有 | E8: UI\BlindBox\BlindBox_Rare_Closed.png | F8: UI\BlindBox\BlindBox_General_Shadow.png | H8: 0f7edc | K8: sol
B9: 1005 | C9: Uncommon | D9: 优秀 | E9: UI\BlindBox\BlindBox_Uncommon_Closed.png | F9: UI\BlindBox\BlindBox_General_Shadow.png | H9: 68c68c | K9: mi
B10: 1006 | C10: Common | D10: 普通 | E10: UI\BlindBox\BlindBox_Common_Closed.png | F10: UI\BlindBox\BlindBox_General_Shadow.png | H10: e4bf8f | K10: do
B11: 2001 | C11: Special1 | D11: 特殊1 | E11: UI\BlindBox\BlindBox_Common_Closed.png | F11: UI\BlindBox\BlindBox_General_Shadow.png | H11: e4bf8f | J11: 实际上特殊品质的盲盒没有显示图片的机会
B12: 2002 | C12: Special2 | D12: 特殊2 | E12: UI\BlindBox\BlindBox_Common_Closed.png | F12: UI\BlindBox\BlindBox_General_Shadow.png | H12: e4bf8f | J12: 实际上特殊品质的盲盒没有显示图片的机会

Sheet RefreshmentConfig
A1: ##var | B1: ItemId | C1: DurationHands | D1: LuckyDealMode | F1: LuckyDealTriggerChance | G1: InteractionHintSfxCue | H1: UseSfxCue | I1: BalloonOffsetY
A2: ##type | B2: int#ref=TbItem | C2: int | D2: ELuckyDealMode | F2: float | G2: string | H2: string | I2: int
A3: ## | B3: 关联 `Item.Id` 的唯一配置。仅允许填写 `ItemType = Refreshment` 的物品； | C3: 使用成功后获得的 BUFF 持续牌局数。每次成功下注并开始新局时消耗 1 局；建议填写 1-99。 | D3: 决定幸运发牌的具体规则。第一版只支持 `GuidedDraw`；其他枚举为后续预留，暂勿配置。 | F3: BUFF 生效期间，每局开始时触发幸运发牌的概率。填写 0-1 小数，例如 `0.75` 表示 75%；未触发也会消耗该局。 | G3: 点击桌面 Refreshment 时，播放交互提示动画所用的 AudioManager 逻辑 Cue。填空则静音；不要填写文件扩展名或资源路径。 | H3: 玩家确认使用 Refreshment 并激活 BUFF 时播放的 AudioManager 逻辑 Cue。可按饮品/食物/器具分别配置；填空则静音。 | I3: 在 PSD 导出定位的基础上，对 UseBalloon 和 StatusBalloon 同时追加的 Y 轴像素偏移。正数向下、负数向上；例如热气使气球偏高时填写正数。
A4: ## | B4: 关联物品 ID | C4: 持续局数 | D4: 幸运发牌模式 | E4: Look校验品质 | F4: 幸运触发概率 | G4: 交互提示音效 | H4: 使用音效 | I4: 气球高度微调 | J4: Look校验品质
B6: 9001 | C6: 30 | D6: GuidedDraw | E6: =LOOKUP(B6,Item!B:B,Item!I:I) -> 史诗 | F6: 0.9 | G6: Refreshment_Hint | H6: Refreshment_BuffStart | I6: 0 | J6: =LOOKUP(B6,Item!B:B,Item!D:D) -> 红茶
B7: 9002 | C7: 20 | D7: GuidedDraw | E7: =LOOKUP(B7,Item!B:B,Item!I:I) -> 稀有 | F7: 0.8 | G7: Refreshment_Hint | H7: Refreshment_BuffStart | I7: 0 | J7: =LOOKUP(B7,Item!B:B,Item!D:D) -> 波尔多
B8: 9003 | C8: 20 | D8: GuidedDraw | E8: =LOOKUP(B8,Item!B:B,Item!I:I) -> 稀有 | F8: 0.8 | G8: Refreshment_Hint | H8: Refreshment_BuffStart | I8: 0 | J8: =LOOKUP(B8,Item!B:B,Item!D:D) -> 勃艮第
B9: 9004 | C9: 30 | D9: GuidedDraw | E9: =LOOKUP(B9,Item!B:B,Item!I:I) -> 史诗 | F9: 0.9 | G9: Refreshment_Hint | H9: Refreshment_BuffStart | I9: 0 | J9: =LOOKUP(B9,Item!B:B,Item!D:D) -> 香槟
B10: 9005 | C10: 20 | D10: GuidedDraw | E10: =LOOKUP(B10,Item!B:B,Item!I:I) -> 稀有 | F10: 0.8 | G10: Refreshment_Hint | H10: Refreshment_BuffStart | I10: 0 | J10: =LOOKUP(B10,Item!B:B,Item!D:D) -> 子弹杯
B11: 9006 | C11: 20 | D11: GuidedDraw | E11: =LOOKUP(B11,Item!B:B,Item!I:I) -> 稀有 | F11: 0.8 | G11: Refreshment_Hint | H11: Refreshment_BuffStart | I11: 0 | J11: =LOOKUP(B11,Item!B:B,Item!D:D) -> 郁金香杯
B12: 9007 | C12: 20 | D12: GuidedDraw | E12: =LOOKUP(B12,Item!B:B,Item!I:I) -> 稀有 | F12: 0.8 | G12: Refreshment_Hint | H12: Refreshment_BuffStart | I12: 0 | J12: =LOOKUP(B12,Item!B:B,Item!D:D) -> 平底杯
B13: 9008 | C13: 30 | D13: GuidedDraw | E13: =LOOKUP(B13,Item!B:B,Item!I:I) -> 史诗 | F13: 0.9 | G13: Refreshment_Hint | H13: Refreshment_BuffStart | I13: 0 | J13: =LOOKUP(B13,Item!B:B,Item!D:D) -> 年份酒
B14: 9009 | C14: 15 | D14: GuidedDraw | E14: =LOOKUP(B14,Item!B:B,Item!I:I) -> 优秀 | F14: 0.7 | G14: Refreshment_Hint | H14: Refreshment_BuffStart | I14: 0 | J14: =LOOKUP(B14,Item!B:B,Item!D:D) -> 凉白开
B15: 9010 | C15: 30 | D15: GuidedDraw | E15: =LOOKUP(B15,Item!B:B,Item!I:I) -> 传说 | F15: 0.9 | G15: Refreshment_Hint | H15: Refreshment_BuffStart | I15: 0 | J15: =LOOKUP(B15,Item!B:B,Item!D:D) -> 威士忌
B16: 9011 | C16: 50 | D16: GuidedDraw | E16: =LOOKUP(B16,Item!B:B,Item!I:I) -> 传说 | F16: 1 | G16: Refreshment_Hint | H16: Refreshment_BuffStart | I16: 100 | J16: =LOOKUP(B16,Item!B:B,Item!D:D) -> 威士忌雪茄

Sheet TabGroup
A1: ##var | B1: Id | C1: TabName | D1: *TabItemTypeList | E1: SortOrder
A2: ##type | B2: int | C2: string | D2: list,EItemType | E2: int
A3: ## | B3: id | C3: 显示名称 | D3: 包含类型 | E3: 在标签栏的顺序
B4: 1001 | C4: Dog | D4: Dog | E4: 1
B5: 1002 | C5: Hat | D5: Headwear | E5: 2
A6: ## | B6: 1003 | C6: Eye | D6: Eyewear | E6: 3
B7: 1004 | C7: Player | D7: Accessory | E7: 4
D8: Clothes
D9: BodyDecoration
B10: 1005 | C10: Theme | D10: Table | E10: 5
D11: Background
B12: 1006 | C12: Refreshment | D12: Refreshment | E12: 6
D13: CardBack
D14: CardFace
D15: Arm

Sheet EquipmentSlotConfig
A1: ##var | B1: ItemType | C1: CanUnequip | D1: DefaultItemId
A2: ##type | B2: EItemType | C2: string | D2: int
A3: ## | B3: id | C3: 可脱光吗 | D3: 默认穿戴物品id
B5: Dog | C5: FALSE | D5: 1001
B6: Headwear | C6: TRUE
A7: ## | B7: Eyewear | C7: TRUE
B8: Arm | C8: FALSE | D8: 4003
B9: Accessory | C9: TRUE
B10: Clothes | C10: TRUE
B11: Table | C11: FALSE | D11: 6001
B12: Background | C12: FALSE | D12: 7004
B13: Refreshment | C13: TRUE
B14: CardBack | C14: FALSE | D14: 10001
B15: CardFace | C15: FALSE | D15: 11002
B16: BodyDecoration | C16: TRUE

Sheet LinkTree
A1: ##var | B1: Id | C1: Key | D1: SortOrder | E1: IsPinned | F1: IsEnabled | G1: BuildChannelMask | H1: TooltipKey | I1: BannerTexturePath | J1: BadgeTexturePath | K1: PreClaimUrl | L1: PostClaimUrl | M1: OpenCheckType | N1: RewardType | O1: RewardItemId | P1: RewardChips | Q1: SequentialPackId | R1: RewardBlindBoxId | S1: SteamReceiptItemDefId | T1: SteamClaimBundleItemDefId
A2: ##type | B2: int | C2: string | D2: int | E2: bool | F2: bool | G2: EBuildChannelMask | H2: string | I2: string | J2: string | K2: string | L2: string | M2: ELinkTreeOpenCheckType | N2: ELinkTreeRewardType | O2: int | P2: int | Q2: int | R2: int | S2: int | T2: int
A3: ## | B3: 唯一 ID | C3: 稳定机器名，代码和存档/Steam 记录用，不要随意改名 | D3: 显示顺序，数字越小越靠前 | E3: 该值为TRUE 的条目始终参与 LinkTree 展示，不因奖励已领取而被替换，并优先占用展示位置 | F3: 是否显示这个入口 | G3: 该条数据允许生效的构建渠道，使用位标记，可同时选择多个渠道。只有 IsEnabled=TRUE 且包含当前构建渠道时，客户端才显示并执行该入口；Steam ItemDef 转换器也只在对应渠道校验相关引用。0 表示不在任何渠道生效。 | H3: Tooltip 本地化 key；当前也可直接作为显示名来源 | I3: Banner 图片路径；可填 res:// 或项目相对路径 | J3: 角标图片路径；空则使用默认礼物角标 | K3: 领奖前点击打开的外部链接，可带 UTM | L3: 领奖后点击打开的外部链接，可带 UTM | M3: 打开校验方式；当前合法值见 ELinkTreeOpenCheckType | N3: 奖励类型；当前合法值见 ELinkTreeRewardType | O3: RewardType=FixedItem 时发放的 Item.Id；不用填 0 | P3: RewardType=FixedChips 时发放的固定筹码数；不用填 0 | Q3: RewardType=SequentialPack 时关联的顺序礼包 ID；当前不用填 0 | R3: RewardType=BlindBox 时填写 BlindBox.Id | S3: 领过奖励的玩家会在Steam服务器上留下凭证，防止再次领奖 Bundle 中永久保留的回执。 Banner 是否已领取只检查这个 ID。 | T3: 客户端调用 AddPromoItem 的目标。 必须指向 Type=Bundle、PromoRule=manual 的定义。
A4: ## | B4: 入口ID | C4: 机器名 | D4: 排序 | E4: 固定 | F4: 启用 | G4: 适用构建渠道 | H4: 提示文本Key | I4: Banner图片 | J4: 角标图片 | K4: 领奖前链接 | L4: 领奖后链接 | M4: 打开校验 | N4: 奖励类型 | O4: 奖励道具ID | P4: 奖励筹码 | Q4: 顺序礼包ID | R4: 奖励盲盒ID | S4: Steam永久领取回执DefID | T4: Steam领奖礼包DefID | U4: 备注
B5: 1001 | C5: TwitterFollow | D5: 30 | E5: FALSE | F5: FALSE | H5: Twitter | I5: UI/LinkTree/Banner_Twitter.png | J5: UI/LinkTree/Icon_Gift.svg | K5: https://x.com/intent/follow?screen_name=LuckyDogRise | L5: https://x.com/LuckyDogRise | M5: ShellOpenOk | N5: FixedItem | O5: 92005 | P5: 0 | Q5: 0 | U5: 墓碑
B6: 1002 | C6: SteamCommunity | D6: 10 | E6: TRUE | F6: FALSE | H6: Steam Community | I6: UI/LinkTree/Banner_SteamCommunity.png | J6: UI/LinkTree/Icon_Gift.svg | K6: https://steamcommunity.com/app/2583700 | L6: https://steamcommunity.com/app/2583700 | M6: ShellOpenOk | N6: FixedChips | O6: 0 | P6: 2500 | Q6: 0 | U6: 墓碑
B7: 1003 | C7: SteamStore | D7: 20 | E7: FALSE | F7: FALSE | H7: Steam Store | I7: UI/LinkTree/Banner_SteamStore.png | J7: UI/LinkTree/Icon_Gift.svg | K7: https://store.steampowered.com/app/2583700?utm_source=linktree&utm_medium=in_game_client&utm_campaign=linktree_pre_claim | L7: https://store.steampowered.com/app/2583700?utm_source=linktree&utm_medium=in_game_client&utm_campaign=linktree_post_claim | M7: ShellOpenOk | N7: FixedChips | O7: 0 | P7: 2500 | Q7: 0 | U7: 墓碑
B8: 1004 | C8: XiaohongshuProfile | D8: 40 | E8: FALSE | F8: FALSE | H8: Xiaohongshu | I8: UI/LinkTree/Banner_Xiaohongshu.png | J8: UI/LinkTree/Icon_Gift.svg | K8: https://www.xiaohongshu.com/user/profile/647bc1b5000000001001f13a | L8: https://www.xiaohongshu.com/user/profile/647bc1b5000000001001f13a | M8: ShellOpenOk | N8: FixedItem | O8: 91012 | P8: 0 | Q8: 0 | U8: 墓碑
B9: 1005 | C9: TwitterFollow | D9: 60 | E9: FALSE | F9: FALSE | H9: Twitter | I9: UI/LinkTree/Banner_Twitter.png | J9: UI/LinkTree/Icon_Gift.svg | K9: https://x.com/intent/follow?screen_name=LuckyDogRise | L9: https://x.com/LuckyDogRise | M9: ShellOpenOk | N9: FixedItem | O9: 92005 | P9: 0 | Q9: 0 | U9: 墓碑
B10: 1006 | C10: SteamCommunity | D10: 80 | E10: TRUE | F10: TRUE | G10: Playtest|Release | H10: Steam Community | I10: UI/LinkTree/Banner_SteamCommunity.png | J10: UI/LinkTree/Icon_Gift.svg | K10: https://steamcommunity.com/app/2583700 | L10: https://steamcommunity.com/app/2583700 | M10: ShellOpenOk | N10: FixedChips | O10: 0 | P10: 2500 | Q10: 0 | S10: 501002 | T10: 601002
B11: 1007 | C11: SteamStore | D11: 100 | E11: FALSE | F11: TRUE | G11: Playtest|Release | H11: Steam Store | I11: UI/LinkTree/Banner_SteamStore.png | J11: UI/LinkTree/Icon_Gift.svg | K11: https://store.steampowered.com/app/2583700?utm_source=linktree&utm_medium=in_game_client&utm_campaign=linktree_pre_claim | L11: https://store.steampowered.com/app/2583700?utm_source=linktree&utm_medium=in_game_client&utm_campaign=linktree_post_claim | M11: ShellOpenOk | N11: FixedChips | O11: 0 | P11: 2500 | Q11: 0 | S11: 501003 | T11: 601003
B12: 1008 | C12: XiaohongshuProfile | D12: 120 | E12: FALSE | F12: FALSE | H12: Xiaohongshu | I12: UI/LinkTree/Banner_Xiaohongshu.png | J12: UI/LinkTree/Icon_Gift.svg | K12: https://www.xiaohongshu.com/user/profile/647bc1b5000000001001f13a | L12: https://www.xiaohongshu.com/user/profile/647bc1b5000000001001f13a | M12: ShellOpenOk | N12: FixedItem | O12: 0 | P12: 0 | Q12: 0 | U12: 墓碑
B13: 1009 | C13: TwitterFollow | D13: 60 | E13: FALSE | F13: TRUE | G13: Playtest|Release | H13: Twitter | I13: UI/LinkTree/Banner_Twitter.png | J13: UI/LinkTree/Icon_Gift.svg | K13: https://x.com/intent/follow?screen_name=LuckyDogRise | L13: https://x.com/LuckyDogRise | M13: ShellOpenOk | N13: FixedItem | O13: 52001 | P13: 0 | Q13: 0 | S13: 501005 | T13: 601005
B14: 1010 | C14: XiaohongshuProfile | D14: 120 | E14: FALSE | F14: FALSE | H14: Xiaohongshu | I14: UI/LinkTree/Banner_Xiaohongshu.png | J14: UI/LinkTree/Icon_Gift.svg | K14: https://www.xiaohongshu.com/user/profile/647bc1b5000000001001f13a | L14: https://www.xiaohongshu.com/user/profile/647bc1b5000000001001f13a | M14: ShellOpenOk | N14: FixedItem | O14: 0 | P14: 0 | Q14: 0 | U14: 墓碑
B15: 1011 | C15: XiaohongshuProfile | D15: 120 | E15: FALSE | F15: TRUE | G15: Playtest|Release | H15: Xiaohongshu | I15: UI/LinkTree/Banner_Xiaohongshu.png | J15: UI/LinkTree/Icon_Gift.svg | K15: https://www.xiaohongshu.com/user/profile/647bc1b5000000001001f13a | L15: https://www.xiaohongshu.com/user/profile/647bc1b5000000001001f13a | M15: ShellOpenOk | N15: FixedItem | O15: 51001 | P15: 0 | Q15: 0 | S15: 501007 | T15: 601007
B16: 410001 | C16: Test01 | D16: 2000 | E16: FALSE | F16: TRUE | G16: Playtest | H16: Test | I16: UI/LinkTree/Banner_Test.png | J16: UI/LinkTree/Icon_Gift.svg | K16: https://www.xiaohongshu.com/user/profile/647bc1b5000000001001f13a | L16: https://www.xiaohongshu.com/user/profile/647bc1b5000000001001f13a | M16: ShellOpenOk | N16: FixedItem | O16: 51001 | P16: 0 | Q16: 0 | S16: 410001 | T16: 410101
B17: 410002 | C17: Test02 | D17: 2000 | E17: FALSE | F17: TRUE | G17: Playtest | H17: Test | I17: UI/LinkTree/Banner_Test.png | J17: UI/LinkTree/Icon_Gift.svg | K17: https://www.xiaohongshu.com/user/profile/647bc1b5000000001001f13a | L17: https://www.xiaohongshu.com/user/profile/647bc1b5000000001001f13a | M17: ShellOpenOk | N17: FixedItem | O17: 51001 | P17: 0 | Q17: 0 | S17: 410002 | T17: 410102
B18: 410003 | C18: Test03 | D18: 2000 | E18: FALSE | F18: TRUE | G18: Playtest | H18: Test | I18: UI/LinkTree/Banner_Test.png | J18: UI/LinkTree/Icon_Gift.svg | K18: https://www.xiaohongshu.com/user/profile/647bc1b5000000001001f13a | L18: https://www.xiaohongshu.com/user/profile/647bc1b5000000001001f13a | M18: ShellOpenOk | N18: FixedItem | O18: 51001 | P18: 0 | Q18: 0 | S18: 410003 | T18: 410103
B19: 410004 | C19: Test04 | D19: 2000 | E19: FALSE | F19: TRUE | G19: Playtest | H19: Test | I19: UI/LinkTree/Banner_Test.png | J19: UI/LinkTree/Icon_Gift.svg | K19: https://www.xiaohongshu.com/user/profile/647bc1b5000000001001f13a | L19: https://www.xiaohongshu.com/user/profile/647bc1b5000000001001f13a | M19: ShellOpenOk | N19: FixedItem | O19: 51001 | P19: 0 | Q19: 0 | S19: 410004 | T19: 410104
B20: 2001 | C20: TwitterFollow | D20: 30 | E20: FALSE | F20: TRUE | G20: Demo | H20: Twitter | I20: UI/LinkTree/Banner_Twitter.png | J20: UI/LinkTree/Icon_Gift.svg | K20: https://x.com/intent/follow?screen_name=LuckyDogRise | L20: https://x.com/LuckyDogRise | M20: ShellOpenOk | N20: FixedItem | O20: 9001 | P20: 0 | Q20: 0
B21: 2002 | C21: SteamCommunity | D21: 10 | E21: TRUE | F21: TRUE | G21: Demo | H21: Steam Community | I21: UI/LinkTree/Banner_SteamCommunity.png | J21: UI/LinkTree/Icon_Gift.svg | K21: steam://openurl/https://steamcommunity.com/app/2583700?utm_source=linktree&utm_medium=in_game_client&utm_campaign=linktree_pre_claim | L21: https://steamcommunity.com/app/2583700 | M21: ShellOpenOk | N21: FixedItem | O21: 9001 | P21: 0 | Q21: 0
B22: 2003 | C22: SteamStore | D22: 20 | E22: FALSE | F22: TRUE | G22: Demo | H22: Steam Store | I22: UI/LinkTree/Banner_SteamStore.png | J22: UI/LinkTree/Icon_Gift.svg | K22: steam://openurl/https://store.steampowered.com/app/2583700?utm_source=linktree&utm_medium=in_game_client&utm_campaign=linktree_pre_claim | L22: https://store.steampowered.com/app/2583700?utm_source=linktree&utm_medium=in_game_client&utm_campaign=linktree_post_claim | M22: ShellOpenOk | N22: FixedItem | O22: 9001 | P22: 0 | Q22: 0
B23: 2004 | C23: XiaohongshuProfile | D23: 40 | E23: FALSE | F23: TRUE | G23: Demo | H23: Xiaohongshu | I23: UI/LinkTree/Banner_Xiaohongshu.png | J23: UI/LinkTree/Icon_Gift.svg | K23: https://www.xiaohongshu.com/user/profile/647bc1b5000000001001f13a | L23: https://www.xiaohongshu.com/user/profile/647bc1b5000000001001f13a | M23: ShellOpenOk | N23: FixedItem | O23: 9001 | P23: 0 | Q23: 0

Sheet SteamItemDef
A1: ##var | B1: Id | C1: Key | E1: Type | F1: Name | G1: Description | H1: PromoRule | I1: GrantedManually | J1: Tradable | K1: Marketable | L1: GameOnly | M1: StoreHidden | N1: AutoStack | O1: Bundle | P1: IsEnabled | Q1: SteamUseDropLimit | R1: SteamDropLimit
A2: ##type | B2: int | C2: string | E2: ESteamItemDefType | F2: string | G2: string | H2: string | I2: bool | J2: bool | K2: bool | L2: bool | M2: bool | N2: bool | O2: string | P2: bool | Q2: bool | R2: int
A3: ## | B3: Steam Inventory 内唯一的 ItemDef ID；发布后不得改作他用 | C3: 稳定机器名；发布后不要改名 | E3: Steam 定义类型；当前合法值见 ESteamItemDefType | F3: Steam 后台英文名称；game_only 回执不向玩家展示 | G3: Steam 后台英文说明；game_only 回执不向玩家展示 | H3: Steam promo 属性；LinkTree 固定填 manual；补偿可填 owns:AppID 只在“Steam 应该通过促销资格直接发放这个 ItemDef”时填写，其余时候留空 | I3: TRUE 时只能由 AddPromoItem/AddPromoItems 指定领取 | J3: 是否允许 Steam 交易 | K3: 是否允许 Steam 社区市场出售 | L3: TRUE 时不显示在 Steam 背包；回执和内部令牌填 TRUE | M3: TRUE 时不在 Steam 物品商店展示 | N3: 是否将同定义物品自动堆叠；一次性回执填 FALSE | O3: Bundle/Generator 的内容配方。 留空表示不输出 bundle； 填写 @AUTO 表示由转换器根据业务表生成； 也可直接填写 Steam 配方，例如 101002x1;101003x1。 | P3: 是否参与导出到 Steam ItemDef 配置 | Q3: 仅用于未被启用 Schedule 引用的 PlaytimeGenerator；TRUE 时显式输出 Steam use_drop_limit | R3: Steam 永久投放上限；退役 PlaytimeGenerator 填 0
A4: ## | B4: Steam物品定义ID | C4: 机器名 | D4: 策划备注 | E4: Steam定义类型 | F4: 英文名称 | G4: 英文说明 | H4: 促销规则 | I4: 仅显式领取 | J4: 可交易 | K4: 可上市场 | L4: 仅游戏内 | M4: 商店隐藏 | N4: 自动堆叠 | O4: 内容配方 | P4: 启用 | Q4: Steam启用投放上限 | R4: Steam投放上限
B5: 401001 | C5: LinkTreeTwitterFollowClaim | D5: 推特领奖 | E5: Item | F5: LinkTree Claim - Twitter Follow | G5: Permanent receipt for the Twitter follow reward. | H5: manual | I5: TRUE | J5: FALSE | K5: FALSE | L5: TRUE | M5: TRUE | N5: FALSE | P5: TRUE | Q5: FALSE | R5: 0
B6: 401002 | C6: LinkTreeSteamCommunityClaim | D6: 社区领奖 | E6: Item | F6: LinkTree Claim - Steam Community | G6: Permanent receipt for the Steam Community reward. | H6: manual | I6: TRUE | J6: FALSE | K6: FALSE | L6: TRUE | M6: TRUE | N6: FALSE | P6: TRUE | Q6: FALSE | R6: 0
B7: 401003 | C7: LinkTreeSteamStoreClaim | D7: 商店页面领奖 | E7: Item | F7: LinkTree Claim - Steam Store | G7: Permanent receipt for the Steam Store reward. | H7: manual | I7: TRUE | J7: FALSE | K7: FALSE | L7: TRUE | M7: TRUE | N7: FALSE | P7: TRUE | Q7: FALSE | R7: 0
B8: 401004 | C8: LinkTreeXiaohongshuProfileClaim | D8: 小红书领奖 | E8: Item | F8: LinkTree Claim - Xiaohongshu Profile | G8: Permanent receipt for the Xiaohongshu profile reward. | H8: manual | I8: TRUE | J8: FALSE | K8: FALSE | L8: TRUE | M8: TRUE | N8: FALSE | P8: TRUE | Q8: FALSE | R8: 0
B9: 401005 | C9: LinkTreeTwitterFollowClaimV2 | D9: 推特领奖回执凭证 | E9: Item | F9: LinkTree Claim - Twitter Follow | G9: Permanent receipt for the Twitter follow reward. | H9: manual | I9: TRUE | J9: FALSE | K9: FALSE | L9: TRUE | M9: TRUE | N9: FALSE | P9: TRUE | Q9: FALSE | R9: 0
B10: 401006 | C10: LinkTreeSteamCommunityClaimV2 | D10: 社区领奖回执凭证 | E10: Item | F10: LinkTree Claim - Steam Community | G10: Permanent receipt for the Steam Community reward. | H10: manual | I10: TRUE | J10: FALSE | K10: FALSE | L10: TRUE | M10: TRUE | N10: FALSE | P10: TRUE | Q10: FALSE | R10: 0
B11: 401007 | C11: LinkTreeSteamStoreClaimV2 | D11: 商店页面领奖回执凭证 | E11: Item | F11: LinkTree Claim - Steam Store | G11: Permanent receipt for the Steam Store reward. | H11: manual | I11: TRUE | J11: FALSE | K11: FALSE | L11: TRUE | M11: TRUE | N11: FALSE | P11: TRUE | Q11: FALSE | R11: 0
B12: 401008 | C12: LinkTreeXiaohongshuProfileClaimV2 | D12: 小红书领奖回执凭证 | E12: Item | F12: LinkTree Claim - Xiaohongshu Profile | G12: Permanent receipt for the Xiaohongshu profile reward. | H12: manual | I12: TRUE | J12: FALSE | K12: FALSE | L12: TRUE | M12: TRUE | N12: FALSE | P12: TRUE | Q12: FALSE | R12: 0
B13: 410001 | C13: LinkTreeTest01 | D13: 测试01 | E13: Item | F13: LinkTree Test 01 | G13: TestDecs01 | H13: manual | I13: TRUE | J13: FALSE | K13: FALSE | L13: TRUE | M13: TRUE | N13: FALSE | P13: TRUE | Q13: FALSE | R13: 0
B14: 410002 | C14: LinkTreeTest02 | D14: 测试02 | E14: Item | F14: LinkTree Test 02 | G14: TestDecs02 | H14: manual | I14: TRUE | J14: FALSE | K14: FALSE | L14: TRUE | M14: TRUE | N14: FALSE | P14: TRUE | Q14: FALSE | R14: 0
B15: 410003 | C15: LinkTreeTest03 | D15: 测试03 | E15: Item | F15: LinkTree Test 03 | G15: TestDecs03 | H15: manual | I15: TRUE | J15: FALSE | K15: FALSE | L15: TRUE | M15: TRUE | N15: FALSE | P15: TRUE | Q15: FALSE | R15: 0
B16: 410004 | C16: LinkTreeTest04 | D16: 测试04 | E16: Item | F16: LinkTree Test 04 | G16: TestDecs04 | H16: manual | I16: TRUE | J16: FALSE | K16: FALSE | L16: TRUE | M16: TRUE | N16: FALSE | P16: TRUE | Q16: FALSE | R16: 0
B17: 410101 | C17: LinkTreeTest01Bundle | D17: 小红书领奖礼包 | E17: Bundle | F17: LinkTree Test01 Bundle | G17: TestDecs01 Bundle | H17: manual | I17: TRUE | J17: FALSE | K17: FALSE | L17: TRUE | M17: TRUE | N17: FALSE | O17: 410001x1;151001x1 | P17: TRUE | Q17: FALSE | R17: 0
B18: 410102 | C18: LinkTreeTest02Bundle | D18: 小红书领奖礼包 | E18: Bundle | F18: LinkTree Test02 Bundle | G18: TestDecs02 Bundle | H18: manual | I18: TRUE | J18: FALSE | K18: FALSE | L18: TRUE | M18: TRUE | N18: FALSE | O18: 410002x1;151001x1 | P18: TRUE | Q18: FALSE | R18: 0
B19: 410103 | C19: LinkTreeTest03Bundle | D19: 小红书领奖礼包 | E19: Bundle | F19: LinkTree Test03 Bundle | G19: TestDecs03 Bundle | H19: manual | I19: TRUE | J19: FALSE | K19: FALSE | L19: TRUE | M19: TRUE | N19: FALSE | O19: 410003x1;151001x1 | P19: TRUE | Q19: FALSE | R19: 0
B20: 410104 | C20: LinkTreeTest04Bundle | D20: 小红书领奖礼包 | E20: Bundle | F20: LinkTree Test04 Bundle | G20: TestDecs04 Bundle | H20: manual | I20: TRUE | J20: FALSE | K20: FALSE | L20: TRUE | M20: TRUE | N20: FALSE | O20: 410004x1;151001x1 | P20: TRUE | Q20: FALSE | R20: 0
A21: ## | B21: 402表示开盒成本
B22: 402001 | C22: DecorationBlindBoxVoucher | D22: 盲盒招待券 | E22: Item | F22: Decoration Blind Box Voucher | G22: Opens one decoration blind box. | I22: FALSE | J22: FALSE | K22: FALSE | L22: TRUE | M22: TRUE | N22: TRUE | P22: TRUE | Q22: FALSE | R22: 0
B23: 402002 | C23: StandardBlindBoxContainer | D23: 标准盲盒券 | E23: Item | F23: Standard Blind Box | G23: A consumable Steam inventory item used to open one standard blind box. | I23: FALSE | J23: FALSE | K23: FALSE | L23: TRUE | M23: TRUE | N23: TRUE | P23: TRUE | Q23: FALSE | R23: 0
B24: 402003 | C24: NewbieBlindBoxContainer | D24: 新手盲盒券 | E24: Item | F24: Newbie Blind Box | G24: A consumable Steam inventory item used to open one newbie blind box. | I24: FALSE | J24: FALSE | K24: FALSE | L24: TRUE | M24: TRUE | N24: TRUE | P24: TRUE | Q24: FALSE | R24: 0
A25: ## | B25: 403盲盒物品生成器
B26: 403001 | C26: DecorationBlindBoxV1Generator | D26: 盲盒物品生成器V1 | E26: Generator | F26: Decoration Blind Box V1 Generator | G26: Generates one decoration reward. | I26: FALSE | J26: FALSE | K26: FALSE | L26: TRUE | M26: TRUE | N26: FALSE | O26: 101002x1;101003x1 | P26: TRUE | Q26: FALSE | R26: 0
B27: 403002 | C27: StandardBlindBoxV1Generator | D27: 标准盲盒物品生成器V1 | E27: Generator | F27: Standard Blind Box V1 Generator | G27: Generates one standard blind box reward. | I27: FALSE | J27: FALSE | K27: FALSE | L27: TRUE | M27: TRUE | N27: FALSE | O27: @AUTO | P27: FALSE | Q27: FALSE | R27: 0
B28: 403003 | C28: NewbieBlindBoxV1Generator | D28: 新手盲盒物品生成器V1 | E28: Generator | F28: Newbie Blind Box V1 Generator | G28: Generates one newbie blind box reward. | I28: FALSE | J28: FALSE | K28: FALSE | L28: TRUE | M28: TRUE | N28: FALSE | O28: @AUTO | P28: FALSE | Q28: FALSE | R28: 0
A29: ## | B29: 404 表示游玩时间用的生成器
B30: 404001 | C30: Schedule1001PlaytimeDrop | D30: 调度1001游玩时间掉落 | E30: PlaytimeGenerator | F30: Schedule 1001 Playtime Drop | G30: Grants the blind box item configured by schedule 1001. | I30: FALSE | J30: FALSE | K30: FALSE | L30: TRUE | M30: TRUE | N30: FALSE | O30: 402001x1 | P30: TRUE | Q30: TRUE | R30: 0
B31: 404002 | C31: Schedule1002PlaytimeDrop | D31: 调度1002游玩时间掉落 | E31: PlaytimeGenerator | F31: Schedule 1002 Playtime Drop | G31: Grants the blind box item configured by schedule 1002. | I31: FALSE | J31: FALSE | K31: FALSE | L31: TRUE | M31: TRUE | N31: FALSE | O31: 402003x1 | P31: TRUE | Q31: TRUE | R31: 0
B32: 404004 | C32: Schedule1004PlaytimeDrop | D32: 调度1004游玩时间掉落 | E32: PlaytimeGenerator | F32: Schedule 1004 Playtime Drop | G32: Grants the blind box item configured by schedule 1004. | I32: FALSE | J32: FALSE | K32: FALSE | L32: TRUE | M32: TRUE | N32: FALSE | O32: 402002x1 | P32: TRUE | Q32: TRUE | R32: 0
B33: 404005 | C33: Schedule1005PlaytimeDrop | D33: 调度1005游玩时间掉落 | E33: PlaytimeGenerator | F33: Schedule 1005 Playtime Drop | G33: Grants the blind box item configured by schedule 1005. | I33: FALSE | J33: FALSE | K33: FALSE | L33: TRUE | M33: TRUE | N33: FALSE | O33: 402003x1 | P33: TRUE | Q33: TRUE | R33: 0
B34: 404007 | C34: Schedule1007PlaytimeDrop | D34: 调度1007游玩时间掉落 | E34: PlaytimeGenerator | F34: Schedule 1007 Playtime Drop | G34: Grants the blind box item configured by schedule 1007. | I34: FALSE | J34: FALSE | K34: FALSE | L34: TRUE | M34: TRUE | N34: FALSE | O34: 402002x1 | P34: TRUE | Q34: TRUE | R34: 0
B35: 404008 | C35: Schedule1008PlaytimeDrop | D35: 调度1008游玩时间掉落 | E35: PlaytimeGenerator | F35: Schedule 1008 Playtime Drop | G35: Grants the blind box item configured by schedule 1008. | I35: FALSE | J35: FALSE | K35: FALSE | L35: TRUE | M35: TRUE | N35: FALSE | O35: 402003x1 | P35: TRUE | Q35: TRUE | R35: 0
B36: 404010 | C36: Schedule1010PlaytimeDrop | D36: 调度1010游玩时间掉落 | E36: PlaytimeGenerator | F36: Schedule 1010 Playtime Drop | G36: Grants the blind box item configured by schedule 1010. | I36: FALSE | J36: FALSE | K36: FALSE | L36: TRUE | M36: TRUE | N36: FALSE | O36: 402002x1 | P36: TRUE | Q36: TRUE | R36: 0
B37: 404011 | C37: Schedule1011PlaytimeDrop | D37: 调度1011游玩时间掉落 | E37: PlaytimeGenerator | F37: Schedule 1011 Playtime Drop | G37: Grants the blind box item configured by schedule 1011. | I37: FALSE | J37: FALSE | K37: FALSE | L37: TRUE | M37: TRUE | N37: FALSE | O37: 402003x1 | P37: TRUE | Q37: TRUE | R37: 0
B38: 404013 | C38: Schedule1013PlaytimeDrop | D38: 调度1013循环游玩时间掉落 | E38: PlaytimeGenerator | F38: Schedule 1013 Playtime Drop | G38: Grants the recurring standard blind box item configured by schedule 1013. | I38: FALSE | J38: FALSE | K38: FALSE | L38: TRUE | M38: TRUE | N38: FALSE | O38: 402002x1 | P38: TRUE | Q38: TRUE | R38: 0
A39: ## | B39: 405 表示掉落窗口用的生成器
B40: 405001 | C40: RecurringDecorationBlindBoxDropV2 | D40: 新版循环装扮盲盒券投放 | E40: PlaytimeGenerator | F40: Recurring Decoration Blind Box Drop V2 | G40: Grants recurring standard blind box vouchers under the Steam playtime drop window. | I40: FALSE | J40: FALSE | K40: FALSE | L40: TRUE | M40: TRUE | N40: FALSE | O40: 402002x1 | P40: TRUE | Q40: TRUE | R40: 0
A41: ## | B41: 406 表示礼包
B42: 406005 | C42: LinkTreeTwitterFollowRewardBundleV2 | D42: 推特领奖礼包 | E42: Bundle | F42: LinkTree Reward Bundle - Twitter Follow | G42: Grants the permanent receipt and fixed item reward for the Twitter follow entry. | H42: manual | I42: TRUE | J42: FALSE | K42: FALSE | L42: TRUE | M42: TRUE | N42: FALSE | O42: 401005x1;192005x1 | P42: TRUE | Q42: FALSE | R42: 0
B43: 406006 | C43: LinkTreeSteamCommunityRewardBundleV2 | D43: Steam社区领奖礼包 | E43: Bundle | F43: LinkTree Reward Bundle - Steam Community | G43: Grants the permanent receipt for the Steam Community entry. The chip reward is granted locally. | H43: manual | I43: TRUE | J43: FALSE | K43: FALSE | L43: TRUE | M43: TRUE | N43: FALSE | O43: 401006x1 | P43: TRUE | Q43: FALSE | R43: 0
B44: 406007 | C44: LinkTreeSteamStoreRewardBundleV2 | D44: Steam商店领奖礼包 | E44: Bundle | F44: LinkTree Reward Bundle - Steam Store | G44: Grants the permanent receipt for the Steam Store entry. The chip reward is granted locally. | H44: manual | I44: TRUE | J44: FALSE | K44: FALSE | L44: TRUE | M44: TRUE | N44: FALSE | O44: 401007x1 | P44: TRUE | Q44: FALSE | R44: 0
B45: 406008 | C45: LinkTreeXiaohongshuProfileRewardBundleV2 | D45: 小红书领奖礼包 | E45: Bundle | F45: LinkTree Reward Bundle - Xiaohongshu Profile | G45: Grants the permanent receipt and fixed item reward for the Xiaohongshu profile entry. | H45: manual | I45: TRUE | J45: FALSE | K45: FALSE | L45: TRUE | M45: TRUE | N45: FALSE | O45: 401008x1;191012x1 | P45: TRUE | Q45: FALSE | R45: 0
A46: ##
A47: ## | B47: Old盲盒开箱成本
B48: 201001 | C48: StandardBlindBoxContainerOfficial | D48: 标准盲盒券 | E48: Item | F48: Standard Blind Box | G48: A consumable Steam inventory item used to open one standard blind box. | I48: FALSE | J48: FALSE | K48: FALSE | L48: TRUE | M48: TRUE | N48: TRUE | P48: TRUE | Q48: FALSE | R48: 0
B49: 201002 | C49: NewbieBlindBoxContainerOfficial | D49: 新手盲盒券 | E49: Item | F49: Newbie Blind Box | G49: A consumable Steam inventory item used to open one newbie blind box. | I49: FALSE | J49: FALSE | K49: FALSE | L49: TRUE | M49: TRUE | N49: TRUE | P49: TRUE | Q49: FALSE | R49: 0
B50: 204001 | C50: DecorationBlindBoxVoucherOfficial | D50: 盲盒招待券 | E50: Item | F50: Decoration Blind Box Voucher | G50: Opens one decoration blind box. | I50: FALSE | J50: FALSE | K50: FALSE | L50: TRUE | M50: TRUE | N50: TRUE | P50: TRUE | Q50: FALSE | R50: 0
A51: ## | B51: 正式盲盒物品生成器
B52: 301001 | C52: StandardBlindBoxV1GeneratorOfficial | D52: 标准盲盒物品生成器V1 | E52: Generator | F52: Standard Blind Box V1 Generator | G52: Generates one standard blind box reward. | I52: FALSE | J52: FALSE | K52: FALSE | L52: TRUE | M52: TRUE | N52: FALSE | O52: @AUTO | P52: TRUE | Q52: FALSE | R52: 0
B53: 301002 | C53: NewbieBlindBoxV1GeneratorOfficial | D53: 新手盲盒物品生成器V1 | E53: Generator | F53: Newbie Blind Box V1 Generator | G53: Generates one newbie blind box reward. | I53: FALSE | J53: FALSE | K53: FALSE | L53: TRUE | M53: TRUE | N53: FALSE | O53: @AUTO | P53: TRUE | Q53: FALSE | R53: 0
A54: ## | B54: 正式新手阶段回执
B55: 500005 | C55: NewbieBlindBoxCheckpoint05ReceiptOfficial | D55: 完成前5个新手盲盒的永久回执 | E55: Item | F55: Newbie Blind Box Checkpoint 5 Receipt | G55: Permanent receipt confirming completion of the first five newbie blind boxes. | H55: manual | I55: TRUE | J55: FALSE | K55: FALSE | L55: TRUE | M55: TRUE | N55: FALSE | P55: TRUE | Q55: FALSE | R55: 0
B56: 500012 | C56: NewbieBlindBoxSequenceCompletedReceiptOfficial | D56: 完成全部12个新手盲盒的永久回执 | E56: Item | F56: Newbie Blind Box Sequence Completed Receipt | G56: Permanent receipt confirming completion of the full newbie blind box sequence. | H56: manual | I56: TRUE | J56: FALSE | K56: FALSE | L56: TRUE | M56: TRUE | N56: FALSE | P56: TRUE | Q56: FALSE | R56: 0
A57: ## | B57: 正式 LinkTree 永久回执
B58: 501001 | C58: LinkTreeTwitterFollowClaimOfficial | D58: 推特领奖回执 | E58: Item | F58: LinkTree Claim - Twitter Follow | G58: Permanent receipt for the Twitter follow reward. | H58: manual | I58: TRUE | J58: FALSE | K58: FALSE | L58: TRUE | M58: TRUE | N58: FALSE | P58: FALSE | Q58: FALSE | R58: 0
B59: 501002 | C59: LinkTreeSteamCommunityClaimOfficial | D59: Steam社区领奖回执 | E59: Item | F59: LinkTree Claim - Steam Community | G59: Permanent receipt for the Steam Community reward. | H59: manual | I59: TRUE | J59: FALSE | K59: FALSE | L59: TRUE | M59: TRUE | N59: FALSE | P59: TRUE | Q59: FALSE | R59: 0
B60: 501003 | C60: LinkTreeSteamStoreClaimOfficial | D60: Steam商店领奖回执 | E60: Item | F60: LinkTree Claim - Steam Store | G60: Permanent receipt for the Steam Store reward. | H60: manual | I60: TRUE | J60: FALSE | K60: FALSE | L60: TRUE | M60: TRUE | N60: FALSE | P60: TRUE | Q60: FALSE | R60: 0
B61: 501004 | C61: LinkTreeXiaohongshuProfileClaimOfficial | D61: 小红书领奖回执 | E61: Item | F61: LinkTree Claim - Xiaohongshu Profile | G61: Permanent receipt for the Xiaohongshu profile reward. | H61: manual | I61: TRUE | J61: FALSE | K61: FALSE | L61: TRUE | M61: TRUE | N61: FALSE | P61: FALSE | Q61: FALSE | R61: 0
B62: 501005 | C62: LinkTreeTwitterFollowClaimPlaytest1 | D62: 推特领奖回执 | E62: Item | F62: LinkTree Claim - Twitter Follow | G62: Permanent receipt for the Twitter follow reward. | H62: manual | I62: TRUE | J62: FALSE | K62: FALSE | L62: TRUE | M62: TRUE | N62: FALSE | P62: TRUE | Q62: FALSE | R62: 0
B63: 501006 | C63: LinkTreeXiaohongshuProfileClaimPlaytest1 | D63: 小红书领奖回执 | E63: Item | F63: LinkTree Claim - Xiaohongshu Profile | G63: Permanent receipt for the Xiaohongshu profile reward. | H63: manual | I63: TRUE | J63: FALSE | K63: FALSE | L63: TRUE | M63: TRUE | N63: FALSE | P63: FALSE | Q63: FALSE | R63: 0
B64: 501007 | C64: LinkTreeXiaohongshuProfileClaimPlaytest2 | D64: 小红书领奖回执 | E64: Item | F64: LinkTree Claim - Xiaohongshu Profile | G64: Permanent receipt for the Xiaohongshu profile reward. | H64: manual | I64: TRUE | J64: FALSE | K64: FALSE | L64: TRUE | M64: TRUE | N64: FALSE | P64: TRUE | Q64: FALSE | R64: 0
A65: ## | B65: 正式 LinkTree 领取 Bundle
B66: 601001 | C66: LinkTreeTwitterFollowRewardBundle | D66: 推特领奖礼包 | E66: Bundle | F66: LinkTree Reward Bundle - Twitter Follow | G66: Grants the permanent receipt and fixed item reward for the Twitter follow entry. | H66: manual | I66: TRUE | J66: FALSE | K66: FALSE | L66: TRUE | M66: TRUE | N66: FALSE | O66: 501001x1;192005x1 | P66: FALSE | Q66: FALSE | R66: 0
B67: 601002 | C67: LinkTreeSteamCommunityRewardBundle | D67: Steam社区领奖礼包 | E67: Bundle | F67: LinkTree Reward Bundle - Steam Community | G67: Grants the permanent receipt for the Steam Community entry. The chip reward is granted locally. | H67: manual | I67: TRUE | J67: FALSE | K67: FALSE | L67: TRUE | M67: TRUE | N67: FALSE | O67: 501002x1 | P67: TRUE | Q67: FALSE | R67: 0
B68: 601003 | C68: LinkTreeSteamStoreRewardBundle | D68: Steam商店领奖礼包 | E68: Bundle | F68: LinkTree Reward Bundle - Steam Store | G68: Grants the permanent receipt for the Steam Store entry. The chip reward is granted locally. | H68: manual | I68: TRUE | J68: FALSE | K68: FALSE | L68: TRUE | M68: TRUE | N68: FALSE | O68: 501003x1 | P68: TRUE | Q68: FALSE | R68: 0
B69: 601004 | C69: LinkTreeXiaohongshuProfileRewardBundle | D69: 小红书领奖礼包 | E69: Bundle | F69: LinkTree Reward Bundle - Xiaohongshu Profile | G69: Grants the permanent receipt and fixed item reward for the Xiaohongshu profile entry. | H69: manual | I69: TRUE | J69: FALSE | K69: FALSE | L69: TRUE | M69: TRUE | N69: FALSE | O69: 501004x1;191012x1 | P69: FALSE | Q69: FALSE | R69: 0
B70: 601005 | C70: LinkTreeTwitterFollowRewardBundle_Playtest | D70: 推特领奖礼包 | E70: Bundle | F70: LinkTree Reward Bundle - Twitter Follow | G70: Grants the permanent receipt and fixed item reward for the Twitter follow entry. | H70: manual | I70: TRUE | J70: FALSE | K70: FALSE | L70: TRUE | M70: TRUE | N70: FALSE | O70: 501005x1;152001x1 | P70: TRUE | Q70: FALSE | R70: 0
B71: 601006 | C71: LinkTreeXiaohongshuProfileRewardBundle_Playtest | D71: 小红书领奖礼包 | E71: Bundle | F71: LinkTree Reward Bundle - Xiaohongshu Profile | G71: Grants the permanent receipt and fixed item reward for the Xiaohongshu profile entry. | H71: manual | I71: TRUE | J71: FALSE | K71: FALSE | L71: TRUE | M71: TRUE | N71: FALSE | O71: 501006x1;153001x1 | P71: FALSE | Q71: FALSE | R71: 0
B72: 601007 | C72: LinkTreeXiaohongshuProfileRewardBundle_Playtest2 | D72: 小红书领奖礼包 | E72: Bundle | F72: LinkTree Reward Bundle - Xiaohongshu Profile | G72: Grants the permanent receipt and fixed item reward for the Xiaohongshu profile entry. | H72: manual | I72: TRUE | J72: FALSE | K72: FALSE | L72: TRUE | M72: TRUE | N72: FALSE | O72: 501007x1;151001x1 | P72: TRUE | Q72: FALSE | R72: 0
A73: ## | B73: Old新手一次性游玩投放
B74: 700001 | C74: NewbieSchedule1001PlaytimeDrop | D74: 新手调度1001游玩投放 | E74: PlaytimeGenerator | F74: Newbie Schedule 1001 Playtime Drop | G74: Grants the blind box item configured by newbie schedule 1001. | I74: FALSE | J74: FALSE | K74: FALSE | L74: TRUE | M74: TRUE | N74: FALSE | O74: 204001x1 | P74: TRUE | Q74: TRUE | R74: 0
B75: 700002 | C75: NewbieSchedule1002PlaytimeDrop | D75: 新手调度1002游玩投放 | E75: PlaytimeGenerator | F75: Newbie Schedule 1002 Playtime Drop | G75: Grants the blind box item configured by newbie schedule 1002. | I75: FALSE | J75: FALSE | K75: FALSE | L75: TRUE | M75: TRUE | N75: FALSE | O75: 201002x1 | P75: TRUE | Q75: TRUE | R75: 0
B76: 700004 | C76: NewbieSchedule1004PlaytimeDrop | D76: 新手调度1004游玩投放 | E76: PlaytimeGenerator | F76: Newbie Schedule 1004 Playtime Drop | G76: Grants the blind box item configured by newbie schedule 1004. | I76: FALSE | J76: FALSE | K76: FALSE | L76: TRUE | M76: TRUE | N76: FALSE | O76: 201001x1 | P76: TRUE | Q76: TRUE | R76: 0
B77: 700005 | C77: NewbieSchedule1005PlaytimeDrop | D77: 新手调度1005游玩投放 | E77: PlaytimeGenerator | F77: Newbie Schedule 1005 Playtime Drop | G77: Grants the blind box item configured by newbie schedule 1005. | I77: FALSE | J77: FALSE | K77: FALSE | L77: TRUE | M77: TRUE | N77: FALSE | O77: 201002x1 | P77: TRUE | Q77: TRUE | R77: 0
B78: 700007 | C78: NewbieSchedule1007PlaytimeDrop | D78: 新手调度1007游玩投放 | E78: PlaytimeGenerator | F78: Newbie Schedule 1007 Playtime Drop | G78: Grants the blind box item configured by newbie schedule 1007. | I78: FALSE | J78: FALSE | K78: FALSE | L78: TRUE | M78: TRUE | N78: FALSE | O78: 201001x1 | P78: TRUE | Q78: TRUE | R78: 0
B79: 700008 | C79: NewbieSchedule1008PlaytimeDrop | D79: 新手调度1008游玩投放 | E79: PlaytimeGenerator | F79: Newbie Schedule 1008 Playtime Drop | G79: Grants the blind box item configured by newbie schedule 1008. | I79: FALSE | J79: FALSE | K79: FALSE | L79: TRUE | M79: TRUE | N79: FALSE | O79: 201002x1 | P79: TRUE | Q79: TRUE | R79: 0
B80: 700010 | C80: NewbieSchedule1010PlaytimeDrop | D80: 新手调度1010游玩投放 | E80: PlaytimeGenerator | F80: Newbie Schedule 1010 Playtime Drop | G80: Grants the blind box item configured by newbie schedule 1010. | I80: FALSE | J80: FALSE | K80: FALSE | L80: TRUE | M80: TRUE | N80: FALSE | O80: 201001x1 | P80: TRUE | Q80: TRUE | R80: 0
B81: 700011 | C81: NewbieSchedule1011PlaytimeDrop | D81: 新手调度1011游玩投放 | E81: PlaytimeGenerator | F81: Newbie Schedule 1011 Playtime Drop | G81: Grants the blind box item configured by newbie schedule 1011. | I81: FALSE | J81: FALSE | K81: FALSE | L81: TRUE | M81: TRUE | N81: FALSE | O81: 201002x1 | P81: TRUE | Q81: TRUE | R81: 0
A82: ## | B82: 正式新手一次性游玩投放
B83: 700101 | C83: NewbieSchedule1001DirectReward | D83: 新手调度1001直接奖励投放 | E83: PlaytimeGenerator | F83: Newbie Schedule 1001 Direct Reward | G83: Generates one standard decoration reward for newbie schedule 1001. | I83: FALSE | J83: FALSE | K83: FALSE | L83: TRUE | M83: TRUE | N83: FALSE | O83: 301001x1 | P83: TRUE | Q83: FALSE | R83: 0
B84: 700102 | C84: NewbieSchedule1002DirectReward | D84: 新手调度1002直接奖励投放 | E84: PlaytimeGenerator | F84: Newbie Schedule 1002 Direct Reward | G84: Generates one newbie decoration reward for newbie schedule 1002. | I84: FALSE | J84: FALSE | K84: FALSE | L84: TRUE | M84: TRUE | N84: FALSE | O84: 301002x1 | P84: TRUE | Q84: FALSE | R84: 0
B85: 700104 | C85: NewbieSchedule1004DirectReward | D85: 新手调度1004直接奖励投放 | E85: PlaytimeGenerator | F85: Newbie Schedule 1004 Direct Reward | G85: Generates one standard decoration reward for newbie schedule 1004. | I85: FALSE | J85: FALSE | K85: FALSE | L85: TRUE | M85: TRUE | N85: FALSE | O85: 301001x1 | P85: TRUE | Q85: FALSE | R85: 0
B86: 700105 | C86: NewbieSchedule1005DirectReward | D86: 新手调度1005直接奖励投放 | E86: PlaytimeGenerator | F86: Newbie Schedule 1005 Direct Reward | G86: Generates one newbie decoration reward for newbie schedule 1005. | I86: FALSE | J86: FALSE | K86: FALSE | L86: TRUE | M86: TRUE | N86: FALSE | O86: 301002x1 | P86: TRUE | Q86: FALSE | R86: 0
B87: 700107 | C87: NewbieSchedule1007DirectReward | D87: 新手调度1007直接奖励投放 | E87: PlaytimeGenerator | F87: Newbie Schedule 1007 Direct Reward | G87: Generates one standard decoration reward for newbie schedule 1007. | I87: FALSE | J87: FALSE | K87: FALSE | L87: TRUE | M87: TRUE | N87: FALSE | O87: 301001x1 | P87: TRUE | Q87: FALSE | R87: 0
B88: 700108 | C88: NewbieSchedule1008DirectReward | D88: 新手调度1008直接奖励投放 | E88: PlaytimeGenerator | F88: Newbie Schedule 1008 Direct Reward | G88: Generates one newbie decoration reward for newbie schedule 1008. | I88: FALSE | J88: FALSE | K88: FALSE | L88: TRUE | M88: TRUE | N88: FALSE | O88: 301002x1 | P88: TRUE | Q88: FALSE | R88: 0
B89: 700110 | C89: NewbieSchedule1010DirectReward | D89: 新手调度1010直接奖励投放 | E89: PlaytimeGenerator | F89: Newbie Schedule 1010 Direct Reward | G89: Generates one standard decoration reward for newbie schedule 1010. | I89: FALSE | J89: FALSE | K89: FALSE | L89: TRUE | M89: TRUE | N89: FALSE | O89: 301001x1 | P89: TRUE | Q89: FALSE | R89: 0
B90: 700111 | C90: NewbieSchedule1011DirectReward | D90: 新手调度1011直接奖励投放 | E90: PlaytimeGenerator | F90: Newbie Schedule 1011 Direct Reward | G90: Generates one newbie decoration reward for newbie schedule 1011. | I90: FALSE | J90: FALSE | K90: FALSE | L90: TRUE | M90: TRUE | N90: FALSE | O90: 301002x1 | P90: TRUE | Q90: FALSE | R90: 0
A91: ## | B91: Old长期循环游玩投放
B92: 701001 | C92: RecurringDecorationBlindBoxDrop | D92: 循环装扮盲盒券投放 | E92: PlaytimeGenerator | F92: Recurring Decoration Blind Box Drop | G92: Grants recurring standard blind box vouchers under the Steam playtime drop window. | I92: FALSE | J92: FALSE | K92: FALSE | L92: TRUE | M92: TRUE | N92: FALSE | O92: 201001x1 | P92: TRUE | Q92: TRUE | R92: 0
A93: ## | B93: 正式长期循环游玩投放
B94: 701101 | C94: RecurringDecorationDirectReward | D94: 循环装扮直接奖励投放 | E94: PlaytimeGenerator | F94: Recurring Decoration Direct Reward | G94: Generates one recurring standard decoration reward under the Steam playtime drop window. | I94: FALSE | J94: FALSE | K94: FALSE | L94: TRUE | M94: TRUE | N94: FALSE | O94: 301001x1 | P94: TRUE | Q94: FALSE | R94: 0

Sheet SteamItemDefIdRange
A1: ##var | B1: Id | C1: StartItemDefId | D1: EndItemDefId | E1: Description | F1: Purpose | G1: Example
A2: ##type | B2: int | C2: int | D2: int | E2: string | F2: string | G2: string
A3: ##
A4: ## | B4: ID | C4: 起始 ItemDef ID | D4: 截止 ItemDef ID | E4: 分段说明 | F4: 用途 | G4: 示例
B5: 1001 | C5: 100000 | D5: 199999 | E5: 正式 Item 使用 SteamItemDefId = 100000 + Item.Id；Item.Id 必须为 1-99999，并由转换器校验。Playtest 专用 Item 使用测试段，不受此公式约束。 | F5: 玩家实际拥有的内容物品 | G5: 101xxx 狗皮肤、102xxx 头饰、103xxx 眼镜
B6: 1002 | C6: 200000 | D6: 299999 | E6: 可消耗库存物品总段；具体用途继续使用子段划分。 | F6: 通常保存在玩家 Steam 库存中、等待被消耗的可堆叠物品 | G6: 熔炼材料
A7: ## | B7: 1003 | C7: 201000 | D7: 229999 | E7: 盲盒开箱成本与 BlindBox 一一对应：SteamOpenCostItemDefId = 200000 + BlindBox.Id。采用该映射的 BlindBox.Id 必须为 1-29999，并由转换器校验。 | F7: 盲盒券和其它盲盒开箱成本 | G7: BlindBox 1001 的开箱成本 ItemDef 为 201001
B8: 1003 | C8: 201000 | D8: 209999 | E8: 历史盲盒券与开箱成本冻结段。 | F8: 兼容旧ID | G8: 201001、201002、204001 只保留兼容，不再分配新定义或改变身份。
B9: 1004 | C9: 210000 | D9: 299999 | E9: 可消耗库存物品的后续功能预留段。 | F9: 可堆叠材料 | G9: 210xxx 可用于熔炼助燃剂等材料
A10: ## | B10: 1005 | C10: 300000 | D10: 399999 | E10: Generator 与交换产物定义总段；同一个权重随机池可以被多种途径使用，不要求与 BlindBox 一一对应。 | F10: 权重随机物品生成器和交换目标 | G10: 301xxx 盲盒 Generator、302xxx 熔炼 Generator
B11: 1005 | C11: 300000 | D11: 399999 | E11: 随机奖励 Generator 总段；同一个权重随机池可以被多种途径使用，不要求与 BlindBox 一一对应。 | F11: 为多种发奖流程提供随机奖励池 | G11: 301xxx 盲盒 Generator、302xxx 熔炼 Generator
A12: ## | B12: 1006 | C12: 301000 | D12: 301999 | E12: 盲盒随机奖池 Generator 子段。 | F12: 盲盒 ExchangeItems 的交换目标 | G12: 标准盲盒、新手盲盒等 Generator
B13: 1006 | C13: 301000 | D13: 301999 | E13: 盲盒奖励池 Generator。可以被 PlaytimeGenerator 直接引用，也兼容历史 Exchange。 | F13: 盲盒装扮奖励池 | G13: 标准盲盒、新手盲盒等 Generator
B14: 1007 | C14: 302000 | D14: 302999 | E14: 熔炼随机奖池 Generator 子段。 | F14: 未来物品回收或熔炼功能的交换目标 | G14: 同品质物品熔炼为更高品质物品
B15: 1008 | C15: 303000 | D15: 399999 | E15: Generator 后续功能预留段。 | F15: 尚未分配的 Generator 和交换目标 | G15: 未来随机池功能
B16: 1009 | C16: 400000 | D16: 499999 | E16: Playtest 专用总段，仅输出到 Playtest，不得进入 Release schema。转换器必须同时检查 SteamItemDef 和 Item.SteamItemDefId。 | F16: 需要真实 Steam 环境验证的测试定义 | G16: 历史测试与后续新功能测试
B17: 1010 | C17: 400000 | D17: 409999 | E17: Playtest 历史测试区，永久冻结。已发布定义继续保留，但不再分配新定义或改变原有身份。 | F17: 保存已经上传到 Playtest 的历史测试定义 | G17: 现有盲盒、LinkTree 与 PlaytimeGenerator 测试定义
B18: 1011 | C18: 410000 | D18: 499999 | E18: 后续 Playtest 测试区。每个新功能按需谨慎分配一小段，不要求跨表对齐子 ID。 | F18: 新增功能的 Steam 实机测试 | G18: 每个新功能通常分配数十个 ItemDef
B19: 1012 | C19: 500000 | D19: 599999 | E19: 永久回执总段。回执保留在玩家库存中，不参与消耗。 | F19: 避免重复领奖，并证明玩家参加过特定入口或活动 | G19: 501xxx LinkTree、502xxx 补偿中心
B20: 1033 | C20: 500001 | D20: 500999 | E20: 新手状态永久回执字段 | F20: 记录一些可获得奖励的新手状态，避免玩家重复走领奖流程 | G20: 500001，新手盲盒阶段开始，500012，新手盲盒阶段走完
B21: 1013 | C21: 501000 | D21: 501999 | E21: LinkTree 永久回执子段。 | F21: 记录每个 LinkTree Banner 是否已经领取 | G21: 一个启用领奖的 Banner 对应一个独立回执
B22: 1014 | C22: 502000 | D22: 502999 | E22: 补偿中心永久回执子段。 | F22: 记录每次补偿活动是否已经领取 | G22: 一个补偿活动对应一个独立回执
B23: 1015 | C23: 503000 | D23: 599999 | E23: 永久回执后续功能预留段。 | F23: 尚未分配的永久资格与活动记录 | G23: 未来活动或其它一次性领取功能
B24: 1016 | C24: 600000 | D24: 699999 | E24: Promo/Claim Bundle 总段。当前 LinkTree 和补偿领取 Bundle 通常与永久回执一一对应，但关联关系始终由表字段和 Bundle 配方决定，不依赖数字相同。 | F24: 发放固定奖励，或发放包含永久回执的一揽子奖励 | G24: 601xxx LinkTree、602xxx 补偿、603xxx 新手礼包
... B30: 1022 | C30: 700000 | D30: 709999 | E30: 固定系统投放总段。 | F30: 长期随客户端维护的系统级 PlaytimeGenerator | G30: 新手一次性投放、长期循环投放
A31: ## | B31: 1023 | C31: 700000 | D31: 700999 | E31: 新手一次性投放子段。 | F31: 前期按游玩时间发放的新手盲盒券 | G31: 新手盲盒队列中的 Steam 投放
B32: 1023 | C32: 700000 | D32: 700999 | E32: 新手一次性 PlaytimeGenerator 总段，同时包含历史券版与新版直接奖励。 | F32: 管理前 12 个新手 Schedule 的一次性 Steam 投放定义 | G32: 7000xx 历史券版、7001xx 新版直接奖励
B33: 1029 | C33: 700000 | D33: 700099 | E33: 历史新手券 PlaytimeGenerator 子段，永久冻结。 | F33: 保存旧版新手券投放定义 | G33: 700001、700002、700004 等历史定义
B34: 1030 | C34: 700100 | D34: 700999 | E34: 新版新手直接奖励 PlaytimeGenerator 子段 | F34: 新手阶段的 PlaytimeGenerator | G34: 前12个奖励当中的装扮奖励
A35: ## | B35: 1024 | C35: 701000 | D35: 701999 | E35: 长期循环投放子段。 | F35: 游戏正常阶段持续运行的循环投放 | G35: 长期循环装扮盲盒券，受掉落窗口控制
B36: 1024 | C36: 701000 | D36: 701999 | E36: 长期循环 PlaytimeGenerator 总段 | F36: 管理游戏正常阶段持续运行的循环投放定义 | G36: 7010xx 历史券版、7011xx 新版直接奖励
B37: 1031 | C37: 701000 | D37: 701099 | E37: 历史循环券 PlaytimeGenerator 子段，永久冻结。 | F37: 保存旧版循环券投放定义 | G37: 701001 历史循环券投放
B38: 1032 | C38: 701100 | D38: 701999 | E38: 新版循环直接奖励 PlaytimeGenerator 子段 | F38: 游戏正常阶段持续运行的循环投放 | G38: 长期循环直接生成装扮，受掉落窗口控制
B39: 1025 | C39: 702000 | D39: 709999 | E39: 固定系统投放预留段。 | F39: 尚未分配的长期系统投放 | G39: 未来固定 PlaytimeGenerator
B40: 1026 | C40: 710000 | D40: 799999 | E40: 限时活动投放段，按顺序分配，不把活动日期编码进 ID。 | F40: 活动期间按游玩时间发放奖励 | G40: 节日活动、版本庆典活动
B41: 1027 | C41: 800000 | D41: 999999 | E41: 未来功能预留段，分配新用途前需要先更新本规划。 | F41: 尚未确定的 Steam Inventory 功能 | G41: Steam 市场、熔炼扩展等
B42: 1028 | C42: 1 | D42: 99999 | E42: 低位保留段，暂不使用。 | F42: 为未来无法预见的兼容需求保留 | G42: 不分配正式或测试定义
